[{
        "model": "MLP",
        "run_type": "train",
        "holdout": 0,
        "Accuracy": 0.9814705919151225,
        "Balanced Accuracy": 0.9529816580001242,
        "AUROC": 0.9853274572101608,
        "AUPRC": 0.9220686022363945
    }, {
        "model": "MLP",
        "run_type": "test",
        "holdout": 0,
        "Accuracy": 0.8576719047142428,
        "Balanced Accuracy": 0.6384037062550595,
        "AUROC": 0.8331440775363476,
        "AUPRC": 0.33287899417446754
    }, {
        "model": "FFNN_1",
        "run_type": "train",
        "holdout": 0,
        "Accuracy": 0.980632326998386,
        "Balanced Accuracy": 0.9526968123328419,
        "AUROC": 0.9868419084513846,
        "AUPRC": 0.9359919942601166
    }, {
        "model": "FFNN_1",
        "run_type": "test",
        "holdout": 0,
        "Accuracy": 0.8635772194975478,
        "Balanced Accuracy": 0.6356985678183308,
        "AUROC": 0.8453548035935982,
        "AUPRC": 0.3526264694668786
    }, {
        "model": "FFNN_2",
        "run_type": "train",
        "holdout": 0,
        "Accuracy": 0.98192100291516,
        "Balanced Accuracy": 0.9503086540735528,
        "AUROC": 0.986762526113591,
        "AUPRC": 0.9339352135653551
    }, {
        "model": "FFNN_2",
        "run_type": "test",
        "holdout": 0,
        "Accuracy": 0.8626263637273546,
        "Balanced Accuracy": 0.6383712487200888,
        "AUROC": 0.8425718800541436,
        "AUPRC": 0.3491842026992984
    }, {
        "model": "FFNN_3",
        "run_type": "train",
        "holdout": 0,
        "Accuracy": 0.9814831033317902,
        "Balanced Accuracy": 0.947228085975331,
        "AUROC": 0.9864980204238708,
        "AUPRC": 0.9362919023616572
    }, {
        "model": "FFNN_3",
        "run_type": "test",
        "holdout": 0,
        "Accuracy": 0.8648783905514964,
        "Balanced Accuracy": 0.6334126878923472,
        "AUROC": 0.8336855031140198,
        "AUPRC": 0.3459917857024345
    }, {
        "model": "MLP",
        "run_type": "train",
        "holdout": 1,
        "Accuracy": 0.9844983547487082,
        "Balanced Accuracy": 0.9606422194185117,
        "AUROC": 0.9901532744554125,
        "AUPRC": 0.9428681783271502
    }, {
        "model": "MLP",
        "run_type": "test",
        "holdout": 1,
        "Accuracy": 0.8833450105094585,
        "Balanced Accuracy": 0.7042731112324268,
        "AUROC": 0.8886935583054362,
        "AUPRC": 0.46821611389656886
    }, {
        "model": "FFNN_1",
        "run_type": "train",
        "holdout": 1,
        "Accuracy": 0.9846484917487207,
        "Balanced Accuracy": 0.9612464668357337,
        "AUROC": 0.9924825722972775,
        "AUPRC": 0.9585943714291547
    }, {
        "model": "FFNN_1",
        "run_type": "test",
        "holdout": 1,
        "Accuracy": 0.8955059553598238,
        "Balanced Accuracy": 0.7205869707570505,
        "AUROC": 0.9051185446684821,
        "AUPRC": 0.5226483257133985
    }, {
        "model": "FFNN_2",
        "run_type": "train",
        "holdout": 1,
        "Accuracy": 0.9864626471655386,
        "Balanced Accuracy": 0.9620355881052518,
        "AUROC": 0.9925784254491342,
        "AUPRC": 0.9595682841029359
    }, {
        "model": "FFNN_2",
        "run_type": "test",
        "holdout": 1,
        "Accuracy": 0.8929536582924632,
        "Balanced Accuracy": 0.7227322750482215,
        "AUROC": 0.9066351576825854,
        "AUPRC": 0.5205240872478916
    }, {
        "model": "FFNN_3",
        "run_type": "train",
        "holdout": 1,
        "Accuracy": 0.9852115054987676,
        "Balanced Accuracy": 0.9541985690328705,
        "AUROC": 0.9920029357431589,
        "AUPRC": 0.9574219260986312
    }, {
        "model": "FFNN_3",
        "run_type": "test",
        "holdout": 1,
        "Accuracy": 0.8961064958462617,
        "Balanced Accuracy": 0.7133733173813698,
        "AUROC": 0.9055590608383396,
        "AUPRC": 0.5337103233756016
    }, {
        "model": "MLP",
        "run_type": "train",
        "holdout": 2,
        "Accuracy": 0.9867003640822251,
        "Balanced Accuracy": 0.9669862012271788,
        "AUROC": 0.992754342648544,
        "AUPRC": 0.9590651345945195
    }, {
        "model": "MLP",
        "run_type": "test",
        "holdout": 2,
        "Accuracy": 0.8953558202382144,
        "Balanced Accuracy": 0.7371188103216779,
        "AUROC": 0.9135474705387389,
        "AUPRC": 0.5502881037412122
    }, {
        "model": "FFNN_1",
        "run_type": "train",
        "holdout": 2,
        "Accuracy": 0.9866127841655511,
        "Balanced Accuracy": 0.9639147318047098,
        "AUROC": 0.9949104439885077,
        "AUPRC": 0.9694161396674109
    }, {
        "model": "FFNN_1",
        "run_type": "test",
        "holdout": 2,
        "Accuracy": 0.9114703232909619,
        "Balanced Accuracy": 0.7575552188879422,
        "AUROC": 0.9337611342055334,
        "AUPRC": 0.6187913808100853
    }, {
        "model": "FFNN_2",
        "run_type": "train",
        "holdout": 2,
        "Accuracy": 0.9882768025823564,
        "Balanced Accuracy": 0.9721267303970098,
        "AUROC": 0.9952649814279384,
        "AUPRC": 0.9698452694307961
    }, {
        "model": "FFNN_2",
        "run_type": "test",
        "holdout": 2,
        "Accuracy": 0.9130217195475928,
        "Balanced Accuracy": 0.7892105995919856,
        "AUROC": 0.9392179053004813,
        "AUPRC": 0.6510351798301486
    }, {
        "model": "FFNN_3",
        "run_type": "train",
        "holdout": 2,
        "Accuracy": 0.9879765285823314,
        "Balanced Accuracy": 0.9641187887239739,
        "AUROC": 0.9952408037622148,
        "AUPRC": 0.9734170162249887
    }, {
        "model": "FFNN_3",
        "run_type": "test",
        "holdout": 2,
        "Accuracy": 0.913872485236713,
        "Balanced Accuracy": 0.7658993228913649,
        "AUROC": 0.938048034057054,
        "AUPRC": 0.6588375214648343
    }, {
        "model": "MLP",
        "run_type": "train",
        "holdout": 3,
        "Accuracy": 0.9877012774156417,
        "Balanced Accuracy": 0.9656158824678329,
        "AUROC": 0.9942663864102571,
        "AUPRC": 0.9677359028779807
    }, {
        "model": "MLP",
        "run_type": "test",
        "holdout": 3,
        "Accuracy": 0.9074166750075068,
        "Balanced Accuracy": 0.748844282108466,
        "AUROC": 0.927744000900706,
        "AUPRC": 0.6147847491175237
    }, {
        "model": "FFNN_1",
        "run_type": "train",
        "holdout": 3,
        "Accuracy": 0.9886771679157231,
        "Balanced Accuracy": 0.968622732253717,
        "AUROC": 0.996196352032893,
        "AUPRC": 0.9763664463320489
    }, {
        "model": "FFNN_1",
        "run_type": "test",
        "holdout": 3,
        "Accuracy": 0.9212791512361125,
        "Balanced Accuracy": 0.7836805503618997,
        "AUROC": 0.949089908157825,
        "AUPRC": 0.6886655836648025
    }, {
        "model": "FFNN_2",
        "run_type": "train",
        "holdout": 3,
        "Accuracy": 0.9898157068324847,
        "Balanced Accuracy": 0.9743657270295631,
        "AUROC": 0.9963728135253427,
        "AUPRC": 0.9783205022494368
    }, {
        "model": "FFNN_2",
        "run_type": "test",
        "holdout": 3,
        "Accuracy": 0.9248823941547393,
        "Balanced Accuracy": 0.80516594028349,
        "AUROC": 0.9531981380599364,
        "AUPRC": 0.7136186751320801
    }, {
        "model": "FFNN_3",
        "run_type": "train",
        "holdout": 3,
        "Accuracy": 0.9885395423323783,
        "Balanced Accuracy": 0.9676005898447632,
        "AUROC": 0.9963800129331396,
        "AUPRC": 0.979451356275963
    }, {
        "model": "FFNN_3",
        "run_type": "test",
        "holdout": 3,
        "Accuracy": 0.9253828445601041,
        "Balanced Accuracy": 0.7948745069874822,
        "AUROC": 0.9500984373299526,
        "AUPRC": 0.7082237061582958
    }, {
        "model": "MLP",
        "run_type": "train",
        "holdout": 4,
        "Accuracy": 0.9890024647490835,
        "Balanced Accuracy": 0.9752754817542302,
        "AUROC": 0.9960011811389271,
        "AUPRC": 0.9749656626275689
    }, {
        "model": "MLP",
        "run_type": "test",
        "holdout": 4,
        "Accuracy": 0.915423881493344,
        "Balanced Accuracy": 0.7803715396712497,
        "AUROC": 0.9425702172655567,
        "AUPRC": 0.674233420076288
    }, {
        "model": "FFNN_1",
        "run_type": "train",
        "holdout": 4,
        "Accuracy": 0.9893152501657763,
        "Balanced Accuracy": 0.9766799205476488,
        "AUROC": 0.9972804225531882,
        "AUPRC": 0.9809912164314543
    }, {
        "model": "FFNN_1",
        "run_type": "test",
        "holdout": 4,
        "Accuracy": 0.9299869882894605,
        "Balanced Accuracy": 0.8140931501043467,
        "AUROC": 0.9570842248102941,
        "AUPRC": 0.7381156866207594
    }, {
        "model": "FFNN_2",
        "run_type": "train",
        "holdout": 4,
        "Accuracy": 0.9913546110826129,
        "Balanced Accuracy": 0.9810432514595306,
        "AUROC": 0.9978057597626863,
        "AUPRC": 0.9851666897661533
    }, {
        "model": "FFNN_2",
        "run_type": "test",
        "holdout": 4,
        "Accuracy": 0.9342408167350615,
        "Balanced Accuracy": 0.8312255584507399,
        "AUROC": 0.9649269501605772,
        "AUPRC": 0.7762045699029486
    }, {
        "model": "FFNN_3",
        "run_type": "train",
        "holdout": 4,
        "Accuracy": 0.9901910493325159,
        "Balanced Accuracy": 0.9720752659163223,
        "AUROC": 0.9972810159784633,
        "AUPRC": 0.9835174717952401
    }, {
        "model": "FFNN_3",
        "run_type": "test",
        "holdout": 4,
        "Accuracy": 0.933039735762186,
        "Balanced Accuracy": 0.8112865373537842,
        "AUROC": 0.9617515274628937,
        "AUPRC": 0.7646864436815098
    }, {
        "model": "MLP",
        "run_type": "train",
        "holdout": 5,
        "Accuracy": 0.989803195415817,
        "Balanced Accuracy": 0.9739809095472945,
        "AUROC": 0.9959175035690345,
        "AUPRC": 0.9759705190839246
    }, {
        "model": "MLP",
        "run_type": "test",
        "holdout": 5,
        "Accuracy": 0.9256330697627865,
        "Balanced Accuracy": 0.805967824377694,
        "AUROC": 0.9517334595578992,
        "AUPRC": 0.7164843503996516
    }, {
        "model": "FFNN_1",
        "run_type": "train",
        "holdout": 5,
        "Accuracy": 0.9897281269158107,
        "Balanced Accuracy": 0.970869292179682,
        "AUROC": 0.9972527649433889,
        "AUPRC": 0.9820451542043392
    }, {
        "model": "FFNN_1",
        "run_type": "test",
        "holdout": 5,
        "Accuracy": 0.9384446001401261,
        "Balanced Accuracy": 0.8388883857950501,
        "AUROC": 0.9666487468652937,
        "AUPRC": 0.7591610158296767
    }, {
        "model": "FFNN_2",
        "run_type": "train",
        "holdout": 5,
        "Accuracy": 0.9912420083326035,
        "Balanced Accuracy": 0.9743218258422873,
        "AUROC": 0.9972987197045456,
        "AUPRC": 0.9845582480635477
    }, {
        "model": "FFNN_2",
        "run_type": "test",
        "holdout": 5,
        "Accuracy": 0.9440496446802122,
        "Balanced Accuracy": 0.8524414145177949,
        "AUROC": 0.9697834717684655,
        "AUPRC": 0.8207691053594668
    }, {
        "model": "FFNN_3",
        "run_type": "train",
        "holdout": 5,
        "Accuracy": 0.9909167114992431,
        "Balanced Accuracy": 0.9712576732843641,
        "AUROC": 0.9976756307354496,
        "AUPRC": 0.9859664733368245
    }, {
        "model": "FFNN_3",
        "run_type": "test",
        "holdout": 5,
        "Accuracy": 0.9384946451806626,
        "Balanced Accuracy": 0.831363628850163,
        "AUROC": 0.9694164916256245,
        "AUPRC": 0.8011764782170084
    }, {
        "model": "MLP",
        "run_type": "train",
        "holdout": 6,
        "Accuracy": 0.9907790859158982,
        "Balanced Accuracy": 0.9750518057194129,
        "AUROC": 0.9967224791966056,
        "AUPRC": 0.9803090237331099
    }, {
        "model": "MLP",
        "run_type": "test",
        "holdout": 6,
        "Accuracy": 0.9301871684516064,
        "Balanced Accuracy": 0.8079750214277449,
        "AUROC": 0.957888159758959,
        "AUPRC": 0.7467709794237223
    }, {
        "model": "FFNN_1",
        "run_type": "train",
        "holdout": 6,
        "Accuracy": 0.990704017415892,
        "Balanced Accuracy": 0.9787868535712156,
        "AUROC": 0.9977567895106116,
        "AUPRC": 0.9859286776503378
    }, {
        "model": "FFNN_1",
        "run_type": "test",
        "holdout": 6,
        "Accuracy": 0.9436492843559203,
        "Balanced Accuracy": 0.8592017185325304,
        "AUROC": 0.9712587606792107,
        "AUPRC": 0.8048131298914729
    }, {
        "model": "FFNN_2",
        "run_type": "train",
        "holdout": 6,
        "Accuracy": 0.9924431043327036,
        "Balanced Accuracy": 0.9776920353745335,
        "AUROC": 0.9978299159330573,
        "AUPRC": 0.9889456704436135
    }, {
        "model": "FFNN_2",
        "run_type": "test",
        "holdout": 6,
        "Accuracy": 0.9487538784906415,
        "Balanced Accuracy": 0.8577434996080167,
        "AUROC": 0.9737361560262565,
        "AUPRC": 0.8518950891336292
    }, {
        "model": "FFNN_3",
        "run_type": "train",
        "holdout": 6,
        "Accuracy": 0.9923930586660328,
        "Balanced Accuracy": 0.9763416389687531,
        "AUROC": 0.9982310614388311,
        "AUPRC": 0.9892721458969362
    }, {
        "model": "FFNN_3",
        "run_type": "test",
        "holdout": 6,
        "Accuracy": 0.9450005004504054,
        "Balanced Accuracy": 0.8444816062547573,
        "AUROC": 0.9743840541079757,
        "AUPRC": 0.8362850938267995
    }, {
        "model": "MLP",
        "run_type": "train",
        "holdout": 7,
        "Accuracy": 0.9913170768326097,
        "Balanced Accuracy": 0.9792277416811949,
        "AUROC": 0.9974183375042763,
        "AUPRC": 0.9840873106048856
    }, {
        "model": "MLP",
        "run_type": "test",
        "holdout": 7,
        "Accuracy": 0.9350915824241818,
        "Balanced Accuracy": 0.8388817420090421,
        "AUROC": 0.9649488955313649,
        "AUPRC": 0.7827494639181509
    }, {
        "model": "FFNN_1",
        "run_type": "train",
        "holdout": 7,
        "Accuracy": 0.9917049307493088,
        "Balanced Accuracy": 0.9772748796693991,
        "AUROC": 0.9983949059268937,
        "AUPRC": 0.9875862272150938
    }, {
        "model": "FFNN_1",
        "run_type": "test",
        "holdout": 7,
        "Accuracy": 0.9469022119907917,
        "Balanced Accuracy": 0.860473579873548,
        "AUROC": 0.9762180092186276,
        "AUPRC": 0.8293105157749937
    }, {
        "model": "FFNN_2",
        "run_type": "train",
        "holdout": 7,
        "Accuracy": 0.9937568030828131,
        "Balanced Accuracy": 0.9830618324416678,
        "AUROC": 0.9989282754891087,
        "AUPRC": 0.9929753148058156
    }, {
        "model": "FFNN_2",
        "run_type": "test",
        "holdout": 7,
        "Accuracy": 0.9534581123010709,
        "Balanced Accuracy": 0.8802287486223968,
        "AUROC": 0.9816760452118357,
        "AUPRC": 0.8726491499509177
    }, {
        "model": "FFNN_3",
        "run_type": "train",
        "holdout": 7,
        "Accuracy": 0.9929310495827443,
        "Balanced Accuracy": 0.9777789088427691,
        "AUROC": 0.9984403332842164,
        "AUPRC": 0.9896260026802377
    }, {
        "model": "FFNN_3",
        "run_type": "test",
        "holdout": 7,
        "Accuracy": 0.9495045540986888,
        "Balanced Accuracy": 0.8604336434741062,
        "AUROC": 0.9785051663234371,
        "AUPRC": 0.8525264177966794
    }, {
        "model": "MLP",
        "run_type": "train",
        "holdout": 8,
        "Accuracy": 0.991955159082663,
        "Balanced Accuracy": 0.9779829089528866,
        "AUROC": 0.9978760511016391,
        "AUPRC": 0.9866095959594048
    }, {
        "model": "MLP",
        "run_type": "test",
        "holdout": 8,
        "Accuracy": 0.9392453207887098,
        "Balanced Accuracy": 0.8349979026021954,
        "AUROC": 0.968693669812972,
        "AUPRC": 0.8087816486143211
    }, {
        "model": "FFNN_1",
        "run_type": "train",
        "holdout": 8,
        "Accuracy": 0.9911168941659264,
        "Balanced Accuracy": 0.9772258794773687,
        "AUROC": 0.9982830425756762,
        "AUPRC": 0.9876389756043267
    }, {
        "model": "FFNN_1",
        "run_type": "test",
        "holdout": 8,
        "Accuracy": 0.9507056350715644,
        "Balanced Accuracy": 0.8737637553694624,
        "AUROC": 0.9786364455700647,
        "AUPRC": 0.8469269641421141
    }, {
        "model": "FFNN_2",
        "run_type": "train",
        "holdout": 8,
        "Accuracy": 0.9936567117494713,
        "Balanced Accuracy": 0.9808332234383423,
        "AUROC": 0.9988535691582344,
        "AUPRC": 0.9919580731460086
    }, {
        "model": "FFNN_2",
        "run_type": "test",
        "holdout": 8,
        "Accuracy": 0.9608647783004705,
        "Balanced Accuracy": 0.8923451967772751,
        "AUROC": 0.9849644368327861,
        "AUPRC": 0.8951636489631037
    }, {
        "model": "FFNN_3",
        "run_type": "train",
        "holdout": 8,
        "Accuracy": 0.9929685838327473,
        "Balanced Accuracy": 0.9778001201498097,
        "AUROC": 0.9986899419267733,
        "AUPRC": 0.9908655970345825
    }, {
        "model": "FFNN_3",
        "run_type": "test",
        "holdout": 8,
        "Accuracy": 0.9536082474226805,
        "Balanced Accuracy": 0.8691728623962375,
        "AUROC": 0.9818028174908756,
        "AUPRC": 0.8707892201705281
    }, {
        "model": "MLP",
        "run_type": "train",
        "holdout": 9,
        "Accuracy": 0.9921553417493463,
        "Balanced Accuracy": 0.9813541042005958,
        "AUROC": 0.998073618727439,
        "AUPRC": 0.985125478735809
    }, {
        "model": "MLP",
        "run_type": "test",
        "holdout": 9,
        "Accuracy": 0.9441497347612852,
        "Balanced Accuracy": 0.8517426748943508,
        "AUROC": 0.9734992025123483,
        "AUPRC": 0.8391810507390742
    }, {
        "model": "FFNN_1",
        "run_type": "train",
        "holdout": 9,
        "Accuracy": 0.9919676704993307,
        "Balanced Accuracy": 0.9789343470050379,
        "AUROC": 0.9985334803246971,
        "AUPRC": 0.9892747940625085
    }, {
        "model": "FFNN_1",
        "run_type": "test",
        "holdout": 9,
        "Accuracy": 0.9568611750575517,
        "Balanced Accuracy": 0.8817742823685684,
        "AUROC": 0.9826496484553001,
        "AUPRC": 0.8678560460628653
    }, {
        "model": "FFNN_2",
        "run_type": "train",
        "holdout": 9,
        "Accuracy": 0.9938944286661578,
        "Balanced Accuracy": 0.9821952396176794,
        "AUROC": 0.9989698129552707,
        "AUPRC": 0.9935467417897499
    }, {
        "model": "FFNN_2",
        "run_type": "test",
        "holdout": 9,
        "Accuracy": 0.9614653187869082,
        "Balanced Accuracy": 0.9111895282536149,
        "AUROC": 0.9861879987091653,
        "AUPRC": 0.9058955392756236
    }, {
        "model": "FFNN_3",
        "run_type": "train",
        "holdout": 9,
        "Accuracy": 0.9933564377494464,
        "Balanced Accuracy": 0.9782553955600152,
        "AUROC": 0.9987958042361105,
        "AUPRC": 0.990539167352583
    }, {
        "model": "FFNN_3",
        "run_type": "test",
        "holdout": 9,
        "Accuracy": 0.9570113101791612,
        "Balanced Accuracy": 0.8816703028193452,
        "AUROC": 0.9841242864960665,
        "AUPRC": 0.8907498516284033
    }, {
        "model": "MLP",
        "run_type": "train",
        "holdout": 10,
        "Accuracy": 0.9931687664994308,
        "Balanced Accuracy": 0.9844293836743441,
        "AUROC": 0.9984922668242091,
        "AUPRC": 0.9900287105532083
    }, {
        "model": "MLP",
        "run_type": "test",
        "holdout": 10,
        "Accuracy": 0.94735261735562,
        "Balanced Accuracy": 0.8667705504274779,
        "AUROC": 0.9758995495906064,
        "AUPRC": 0.8462357422193947
    }, {
        "model": "FFNN_1",
        "run_type": "train",
        "holdout": 10,
        "Accuracy": 0.9919176248326598,
        "Balanced Accuracy": 0.9806059269719649,
        "AUROC": 0.9987887184466069,
        "AUPRC": 0.9910225261246727
    }, {
        "model": "FFNN_1",
        "run_type": "test",
        "holdout": 10,
        "Accuracy": 0.9575618056250625,
        "Balanced Accuracy": 0.8802819725938547,
        "AUROC": 0.9834305082211386,
        "AUPRC": 0.876389981037947
    }, {
        "model": "FFNN_2",
        "run_type": "train",
        "holdout": 10,
        "Accuracy": 0.9943948853328662,
        "Balanced Accuracy": 0.9840362636120665,
        "AUROC": 0.9992825073874536,
        "AUPRC": 0.9952669840737655
    }, {
        "model": "FFNN_2",
        "run_type": "test",
        "holdout": 10,
        "Accuracy": 0.9653187869082174,
        "Balanced Accuracy": 0.9160108169186996,
        "AUROC": 0.9877207115448149,
        "AUPRC": 0.9200909066313802
    }, {
        "model": "FFNN_3",
        "run_type": "train",
        "holdout": 10,
        "Accuracy": 0.9935941546661329,
        "Balanced Accuracy": 0.9793341014544109,
        "AUROC": 0.998960116248096,
        "AUPRC": 0.992797100588806
    }, {
        "model": "FFNN_3",
        "run_type": "test",
        "holdout": 10,
        "Accuracy": 0.9588129316384746,
        "Balanced Accuracy": 0.8840102417952497,
        "AUROC": 0.9844741720915452,
        "AUPRC": 0.8950089837998068
    }, {
        "model": "MLP",
        "run_type": "train",
        "holdout": 11,
        "Accuracy": 0.9928059354160672,
        "Balanced Accuracy": 0.982524479329969,
        "AUROC": 0.9985263715044584,
        "AUPRC": 0.9908667014248211
    }, {
        "model": "MLP",
        "run_type": "test",
        "holdout": 11,
        "Accuracy": 0.9531077970173156,
        "Balanced Accuracy": 0.8805972515553766,
        "AUROC": 0.9801806652957132,
        "AUPRC": 0.8674721015174237
    }, {
        "model": "FFNN_1",
        "run_type": "train",
        "holdout": 11,
        "Accuracy": 0.9911294055825941,
        "Balanced Accuracy": 0.9814826041871689,
        "AUROC": 0.9985708638139356,
        "AUPRC": 0.9894117067481888
    }, {
        "model": "FFNN_1",
        "run_type": "test",
        "holdout": 11,
        "Accuracy": 0.9595636072465219,
        "Balanced Accuracy": 0.8933092948629386,
        "AUROC": 0.9856071770769389,
        "AUPRC": 0.8981519147605411
    }, {
        "model": "FFNN_2",
        "run_type": "train",
        "holdout": 11,
        "Accuracy": 0.9945450223328788,
        "Balanced Accuracy": 0.9829406493196406,
        "AUROC": 0.9990617547206136,
        "AUPRC": 0.9955035929949332
    }, {
        "model": "FFNN_2",
        "run_type": "test",
        "holdout": 11,
        "Accuracy": 0.9683715343809428,
        "Balanced Accuracy": 0.9101829885331201,
        "AUROC": 0.9890830806545552,
        "AUPRC": 0.9268263917539954
    }, {
        "model": "FFNN_3",
        "run_type": "train",
        "holdout": 11,
        "Accuracy": 0.993331414916111,
        "Balanced Accuracy": 0.9796105877325376,
        "AUROC": 0.999137303976393,
        "AUPRC": 0.9939895780814815
    }, {
        "model": "FFNN_3",
        "run_type": "test",
        "holdout": 11,
        "Accuracy": 0.9610649584626163,
        "Balanced Accuracy": 0.8890594577585016,
        "AUROC": 0.9864633044295482,
        "AUPRC": 0.9069096253642787
    }, {
        "model": "MLP",
        "run_type": "train",
        "holdout": 12,
        "Accuracy": 0.9930436523327536,
        "Balanced Accuracy": 0.9819033235147168,
        "AUROC": 0.998698884761218,
        "AUPRC": 0.9915011718427118
    }, {
        "model": "MLP",
        "run_type": "test",
        "holdout": 12,
        "Accuracy": 0.9549594635171654,
        "Balanced Accuracy": 0.8788113011757881,
        "AUROC": 0.9801076941747162,
        "AUPRC": 0.8713813238893706
    }, {
        "model": "FFNN_1",
        "run_type": "train",
        "holdout": 12,
        "Accuracy": 0.9919051134159921,
        "Balanced Accuracy": 0.9814960057719322,
        "AUROC": 0.9989068192885845,
        "AUPRC": 0.9904739791885151
    }, {
        "model": "FFNN_1",
        "run_type": "test",
        "holdout": 12,
        "Accuracy": 0.9600640576518867,
        "Balanced Accuracy": 0.8873608590422677,
        "AUROC": 0.9852373232817395,
        "AUPRC": 0.8845407273763352
    }, {
        "model": "FFNN_2",
        "run_type": "train",
        "holdout": 12,
        "Accuracy": 0.9951330589162611,
        "Balanced Accuracy": 0.9853977869336721,
        "AUROC": 0.9992696193880835,
        "AUPRC": 0.9958770548532537
    }, {
        "model": "FFNN_2",
        "run_type": "test",
        "holdout": 12,
        "Accuracy": 0.969422480232209,
        "Balanced Accuracy": 0.9145534330726488,
        "AUROC": 0.990471337196652,
        "AUPRC": 0.9324910590392272
    }, {
        "model": "FFNN_3",
        "run_type": "train",
        "holdout": 12,
        "Accuracy": 0.993418994832785,
        "Balanced Accuracy": 0.9792351153548875,
        "AUROC": 0.9990464822724677,
        "AUPRC": 0.9938072564544531
    }, {
        "model": "FFNN_3",
        "run_type": "test",
        "holdout": 12,
        "Accuracy": 0.9622159943949554,
        "Balanced Accuracy": 0.8997177238305629,
        "AUROC": 0.9876995275690961,
        "AUPRC": 0.9165018911505274
    }, {
        "model": "MLP",
        "run_type": "train",
        "holdout": 13,
        "Accuracy": 0.9929060267494089,
        "Balanced Accuracy": 0.9833365369085878,
        "AUROC": 0.9986278917525359,
        "AUPRC": 0.9914038242957818
    }, {
        "model": "MLP",
        "run_type": "test",
        "holdout": 13,
        "Accuracy": 0.9535081573416074,
        "Balanced Accuracy": 0.8732704696090754,
        "AUROC": 0.9811670894496998,
        "AUPRC": 0.8727135858443417
    }, {
        "model": "FFNN_1",
        "run_type": "train",
        "holdout": 13,
        "Accuracy": 0.9930936979994245,
        "Balanced Accuracy": 0.9819316052574378,
        "AUROC": 0.9989653549726436,
        "AUPRC": 0.9935386562622426
    }, {
        "model": "FFNN_1",
        "run_type": "test",
        "holdout": 13,
        "Accuracy": 0.9639675708137324,
        "Balanced Accuracy": 0.8982528611200411,
        "AUROC": 0.9877839932995269,
        "AUPRC": 0.9067432585335138
    }, {
        "model": "FFNN_2",
        "run_type": "train",
        "holdout": 13,
        "Accuracy": 0.9954958899996247,
        "Balanced Accuracy": 0.985319519283458,
        "AUROC": 0.9991521288605865,
        "AUPRC": 0.9953047310743433
    }, {
        "model": "FFNN_2",
        "run_type": "test",
        "holdout": 13,
        "Accuracy": 0.9712741467320588,
        "Balanced Accuracy": 0.9239082153471849,
        "AUROC": 0.9897252682732544,
        "AUPRC": 0.9368751716005468
    }, {
        "model": "FFNN_3",
        "run_type": "train",
        "holdout": 13,
        "Accuracy": 0.9938068487494839,
        "Balanced Accuracy": 0.9810125054281523,
        "AUROC": 0.9990728087057775,
        "AUPRC": 0.9939245942749252
    }, {
        "model": "FFNN_3",
        "run_type": "test",
        "holdout": 13,
        "Accuracy": 0.9676208587728956,
        "Balanced Accuracy": 0.9137241019142528,
        "AUROC": 0.9898603790563599,
        "AUPRC": 0.9245702319765466
    }, {
        "model": "MLP",
        "run_type": "train",
        "holdout": 14,
        "Accuracy": 0.9939820085828318,
        "Balanced Accuracy": 0.9813948018126171,
        "AUROC": 0.9989610106083099,
        "AUPRC": 0.9926253458337608
    }, {
        "model": "MLP",
        "run_type": "test",
        "holdout": 14,
        "Accuracy": 0.9582624361925733,
        "Balanced Accuracy": 0.8833214862716662,
        "AUROC": 0.9842305502304977,
        "AUPRC": 0.8907937247745162
    }, {
        "model": "FFNN_1",
        "run_type": "train",
        "holdout": 14,
        "Accuracy": 0.9929560724160796,
        "Balanced Accuracy": 0.9847813700760154,
        "AUROC": 0.9992218912603227,
        "AUPRC": 0.9932145372106591
    }, {
        "model": "FFNN_1",
        "run_type": "test",
        "holdout": 14,
        "Accuracy": 0.9645681113001702,
        "Balanced Accuracy": 0.91199889121229,
        "AUROC": 0.9884681804526946,
        "AUPRC": 0.9066544624017234
    }, {
        "model": "FFNN_2",
        "run_type": "train",
        "holdout": 14,
        "Accuracy": 0.9954333329162861,
        "Balanced Accuracy": 0.9867479369105868,
        "AUROC": 0.9992470776722444,
        "AUPRC": 0.9954579096482471
    }, {
        "model": "FFNN_2",
        "run_type": "test",
        "holdout": 14,
        "Accuracy": 0.9729756781102993,
        "Balanced Accuracy": 0.9346887590112641,
        "AUROC": 0.9908407243303572,
        "AUPRC": 0.9434878504982128
    }, {
        "model": "FFNN_3",
        "run_type": "train",
        "holdout": 14,
        "Accuracy": 0.9929185381660766,
        "Balanced Accuracy": 0.9830602970593267,
        "AUROC": 0.9989046935517336,
        "AUPRC": 0.9924323521721632
    }, {
        "model": "FFNN_3",
        "run_type": "test",
        "holdout": 14,
        "Accuracy": 0.9649184265839256,
        "Balanced Accuracy": 0.9140851259827615,
        "AUROC": 0.9873890994309996,
        "AUPRC": 0.918585730286308
    }, {
        "model": "MLP",
        "run_type": "train",
        "holdout": 15,
        "Accuracy": 0.9943823739161985,
        "Balanced Accuracy": 0.9882316290696825,
        "AUROC": 0.9991303817051088,
        "AUPRC": 0.9932222061976524
    }, {
        "model": "MLP",
        "run_type": "test",
        "holdout": 15,
        "Accuracy": 0.9627164448003203,
        "Balanced Accuracy": 0.9066094544587135,
        "AUROC": 0.9860374021327952,
        "AUPRC": 0.9079516441720963
    }, {
        "model": "FFNN_1",
        "run_type": "train",
        "holdout": 15,
        "Accuracy": 0.9934690404994557,
        "Balanced Accuracy": 0.9857323152704353,
        "AUROC": 0.999439578536319,
        "AUPRC": 0.9959440055387995
    }, {
        "model": "FFNN_1",
        "run_type": "test",
        "holdout": 15,
        "Accuracy": 0.9675207686918227,
        "Balanced Accuracy": 0.9178217091270908,
        "AUROC": 0.9903985748452704,
        "AUPRC": 0.9268828383519969
    }, {
        "model": "FFNN_2",
        "run_type": "train",
        "holdout": 15,
        "Accuracy": 0.9958462096663205,
        "Balanced Accuracy": 0.9876423186195648,
        "AUROC": 0.9996339018992327,
        "AUPRC": 0.9967399285627875
    }, {
        "model": "FFNN_2",
        "run_type": "test",
        "holdout": 15,
        "Accuracy": 0.9731258132319087,
        "Balanced Accuracy": 0.9319412157814012,
        "AUROC": 0.9927284191962237,
        "AUPRC": 0.9475011475873403
    }, {
        "model": "FFNN_3",
        "run_type": "train",
        "holdout": 15,
        "Accuracy": 0.9944824652495402,
        "Balanced Accuracy": 0.9837552279960633,
        "AUROC": 0.999428672715551,
        "AUPRC": 0.9955930518352888
    }, {
        "model": "FFNN_3",
        "run_type": "test",
        "holdout": 15,
        "Accuracy": 0.969622660394355,
        "Balanced Accuracy": 0.9159883434835893,
        "AUROC": 0.9908066580412886,
        "AUPRC": 0.9331372167098302
    }, {
        "model": "MLP",
        "run_type": "train",
        "holdout": 16,
        "Accuracy": 0.9940820999161735,
        "Balanced Accuracy": 0.9877314099475918,
        "AUROC": 0.9990199155518218,
        "AUPRC": 0.992665964683603
    }, {
        "model": "MLP",
        "run_type": "test",
        "holdout": 16,
        "Accuracy": 0.9632669402462216,
        "Balanced Accuracy": 0.9091864697541826,
        "AUROC": 0.9870675082587417,
        "AUPRC": 0.9074645109907776
    }, {
        "model": "FFNN_1",
        "run_type": "train",
        "holdout": 16,
        "Accuracy": 0.9929560724160796,
        "Balanced Accuracy": 0.9836009105554265,
        "AUROC": 0.99932822569973,
        "AUPRC": 0.994032173985549
    }, {
        "model": "FFNN_1",
        "run_type": "test",
        "holdout": 16,
        "Accuracy": 0.9690721649484536,
        "Balanced Accuracy": 0.9179431516406455,
        "AUROC": 0.991376771020282,
        "AUPRC": 0.9291224742029348
    }, {
        "model": "FFNN_2",
        "run_type": "train",
        "holdout": 16,
        "Accuracy": 0.9959212781663268,
        "Balanced Accuracy": 0.9872597758062343,
        "AUROC": 0.9995454585025535,
        "AUPRC": 0.997101543021445
    }, {
        "model": "FFNN_2",
        "run_type": "test",
        "holdout": 16,
        "Accuracy": 0.9754779301371234,
        "Balanced Accuracy": 0.9344034323493235,
        "AUROC": 0.9939755597586202,
        "AUPRC": 0.9565694881065779
    }, {
        "model": "FFNN_3",
        "run_type": "train",
        "holdout": 16,
        "Accuracy": 0.9944949766662079,
        "Balanced Accuracy": 0.9834789881468022,
        "AUROC": 0.9992692693209096,
        "AUPRC": 0.9943972051034502
    }, {
        "model": "FFNN_3",
        "run_type": "test",
        "holdout": 16,
        "Accuracy": 0.9701231107997198,
        "Balanced Accuracy": 0.916082338932952,
        "AUROC": 0.992145301098224,
        "AUPRC": 0.9456516905465989
    }, {
        "model": "MLP",
        "run_type": "train",
        "holdout": 17,
        "Accuracy": 0.9945074880828756,
        "Balanced Accuracy": 0.9875940577141317,
        "AUROC": 0.9991869398167126,
        "AUPRC": 0.9943804234224528
    }, {
        "model": "MLP",
        "run_type": "test",
        "holdout": 17,
        "Accuracy": 0.9651186067460714,
        "Balanced Accuracy": 0.9158976883480789,
        "AUROC": 0.9883139611094626,
        "AUPRC": 0.9181860722730485
    }, {
        "model": "FFNN_1",
        "run_type": "train",
        "holdout": 17,
        "Accuracy": 0.9935691318327974,
        "Balanced Accuracy": 0.9835223964763466,
        "AUROC": 0.9993255886805594,
        "AUPRC": 0.9945602477320709
    }, {
        "model": "FFNN_1",
        "run_type": "test",
        "holdout": 17,
        "Accuracy": 0.971073966569913,
        "Balanced Accuracy": 0.923983912753753,
        "AUROC": 0.990669005181097,
        "AUPRC": 0.9331073675005173
    }, {
        "model": "FFNN_2",
        "run_type": "train",
        "holdout": 17,
        "Accuracy": 0.9962090407496841,
        "Balanced Accuracy": 0.9883195450625275,
        "AUROC": 0.9995631438040482,
        "AUPRC": 0.9971192846717419
    }, {
        "model": "FFNN_2",
        "run_type": "test",
        "holdout": 17,
        "Accuracy": 0.9760784706235612,
        "Balanced Accuracy": 0.9400299454224645,
        "AUROC": 0.9939154709509729,
        "AUPRC": 0.9529438725897709
    }, {
        "model": "FFNN_3",
        "run_type": "train",
        "holdout": 17,
        "Accuracy": 0.9948202734995684,
        "Balanced Accuracy": 0.983001762142959,
        "AUROC": 0.9994304030914494,
        "AUPRC": 0.9961026695565326
    }, {
        "model": "FFNN_3",
        "run_type": "test",
        "holdout": 17,
        "Accuracy": 0.9714242818536682,
        "Balanced Accuracy": 0.9190835863682479,
        "AUROC": 0.991108096805341,
        "AUPRC": 0.9396420050816456
    }, {
        "model": "MLP",
        "run_type": "train",
        "holdout": 18,
        "Accuracy": 0.9948703191662392,
        "Balanced Accuracy": 0.9861464570200345,
        "AUROC": 0.9993358550145823,
        "AUPRC": 0.995099288952046
    }, {
        "model": "MLP",
        "run_type": "test",
        "holdout": 18,
        "Accuracy": 0.9650185166649985,
        "Balanced Accuracy": 0.9139528642908832,
        "AUROC": 0.9887133251038807,
        "AUPRC": 0.9196574111440874
    }, {
        "model": "FFNN_1",
        "run_type": "train",
        "holdout": 18,
        "Accuracy": 0.9929560724160796,
        "Balanced Accuracy": 0.9788790724730712,
        "AUROC": 0.9991614010345437,
        "AUPRC": 0.9939035039995235
    }, {
        "model": "FFNN_1",
        "run_type": "test",
        "holdout": 18,
        "Accuracy": 0.9683715343809428,
        "Balanced Accuracy": 0.911882422327817,
        "AUROC": 0.9907289466219563,
        "AUPRC": 0.9270016525704823
    }, {
        "model": "FFNN_2",
        "run_type": "train",
        "holdout": 18,
        "Accuracy": 0.9964092234163674,
        "Balanced Accuracy": 0.9882910168909407,
        "AUROC": 0.9994617563665434,
        "AUPRC": 0.9967845501484855
    }, {
        "model": "FFNN_2",
        "run_type": "test",
        "holdout": 18,
        "Accuracy": 0.9787809028125313,
        "Balanced Accuracy": 0.9421236590574071,
        "AUROC": 0.994490324228301,
        "AUPRC": 0.9645483522095071
    }, {
        "model": "FFNN_3",
        "run_type": "train",
        "holdout": 18,
        "Accuracy": 0.9946451136662204,
        "Balanced Accuracy": 0.9837527068982594,
        "AUROC": 0.9993689240794428,
        "AUPRC": 0.9955078592626936
    }, {
        "model": "FFNN_3",
        "run_type": "test",
        "holdout": 18,
        "Accuracy": 0.9724752277049344,
        "Balanced Accuracy": 0.9270417244743592,
        "AUROC": 0.9930067213746216,
        "AUPRC": 0.9471089333490094
    }, {
        "model": "MLP",
        "run_type": "train",
        "holdout": 19,
        "Accuracy": 0.9949078534162423,
        "Balanced Accuracy": 0.9831929103351913,
        "AUROC": 0.999325663146603,
        "AUPRC": 0.9954084905645977
    }, {
        "model": "MLP",
        "run_type": "test",
        "holdout": 19,
        "Accuracy": 0.9656190571514363,
        "Balanced Accuracy": 0.9025850394170543,
        "AUROC": 0.988729658256174,
        "AUPRC": 0.9212274667801679
    }, {
        "model": "FFNN_1",
        "run_type": "train",
        "holdout": 19,
        "Accuracy": 0.9941571684161797,
        "Balanced Accuracy": 0.9842324539999068,
        "AUROC": 0.9993292659212661,
        "AUPRC": 0.9937485506533285
    }, {
        "model": "FFNN_1",
        "run_type": "test",
        "holdout": 19,
        "Accuracy": 0.9688719847863076,
        "Balanced Accuracy": 0.9204735867506648,
        "AUROC": 0.9901213901983452,
        "AUPRC": 0.9152882664489455
    }, {
        "model": "FFNN_2",
        "run_type": "train",
        "holdout": 19,
        "Accuracy": 0.9966969859997248,
        "Balanced Accuracy": 0.9915228316651175,
        "AUROC": 0.9995877275784009,
        "AUPRC": 0.9974309259772268
    }, {
        "model": "FFNN_2",
        "run_type": "test",
        "holdout": 19,
        "Accuracy": 0.9791812631368232,
        "Balanced Accuracy": 0.9506582591949446,
        "AUROC": 0.995062524903452,
        "AUPRC": 0.9587021616716893
    }, {
        "model": "FFNN_3",
        "run_type": "train",
        "holdout": 19,
        "Accuracy": 0.9948828305829069,
        "Balanced Accuracy": 0.9844064473652432,
        "AUROC": 0.9995271943619164,
        "AUPRC": 0.9965073165692074
    }, {
        "model": "FFNN_3",
        "run_type": "test",
        "holdout": 19,
        "Accuracy": 0.9700230207186468,
        "Balanced Accuracy": 0.9196134682142243,
        "AUROC": 0.9913679535741566,
        "AUPRC": 0.9389226580335779
    }, {
        "model": "MLP",
        "run_type": "train",
        "holdout": 20,
        "Accuracy": 0.9947326935828944,
        "Balanced Accuracy": 0.9856909351809633,
        "AUROC": 0.9992895279232079,
        "AUPRC": 0.9944534003949685
    }, {
        "model": "MLP",
        "run_type": "test",
        "holdout": 20,
        "Accuracy": 0.9659693724351917,
        "Balanced Accuracy": 0.9090142716628625,
        "AUROC": 0.9894431959612068,
        "AUPRC": 0.923649304536012
    }, {
        "model": "FFNN_1",
        "run_type": "train",
        "holdout": 20,
        "Accuracy": 0.9931437436660953,
        "Balanced Accuracy": 0.9829514729974533,
        "AUROC": 0.999279838892945,
        "AUPRC": 0.9936448106474507
    }, {
        "model": "FFNN_1",
        "run_type": "test",
        "holdout": 20,
        "Accuracy": 0.9707736963266941,
        "Balanced Accuracy": 0.9215483081715596,
        "AUROC": 0.9908997692899256,
        "AUPRC": 0.9323665929253566
    }, {
        "model": "FFNN_2",
        "run_type": "train",
        "holdout": 20,
        "Accuracy": 0.9965468489997122,
        "Balanced Accuracy": 0.9894075960615416,
        "AUROC": 0.999639626572291,
        "AUPRC": 0.9966046630385255
    }, {
        "model": "FFNN_2",
        "run_type": "test",
        "holdout": 20,
        "Accuracy": 0.9787308577719948,
        "Balanced Accuracy": 0.9441724626638262,
        "AUROC": 0.9933353001887254,
        "AUPRC": 0.9572838984549894
    }, {
        "model": "FFNN_3",
        "run_type": "train",
        "holdout": 20,
        "Accuracy": 0.995095524666258,
        "Balanced Accuracy": 0.9883513336185152,
        "AUROC": 0.9994386903176348,
        "AUPRC": 0.9958839137596176
    }, {
        "model": "FFNN_3",
        "run_type": "test",
        "holdout": 20,
        "Accuracy": 0.9724251826643979,
        "Balanced Accuracy": 0.9349441333736234,
        "AUROC": 0.9929554868547966,
        "AUPRC": 0.9519711488844637
    }, {
        "model": "MLP",
        "run_type": "train",
        "holdout": 21,
        "Accuracy": 0.9955959813329663,
        "Balanced Accuracy": 0.9864621055278416,
        "AUROC": 0.9994672161861481,
        "AUPRC": 0.9953183351989442
    }, {
        "model": "MLP",
        "run_type": "test",
        "holdout": 21,
        "Accuracy": 0.9684716244620158,
        "Balanced Accuracy": 0.9106172047728074,
        "AUROC": 0.990585325406867,
        "AUPRC": 0.9327483270989296
    }, {
        "model": "FFNN_1",
        "run_type": "train",
        "holdout": 21,
        "Accuracy": 0.9928684924994057,
        "Balanced Accuracy": 0.9846374402646065,
        "AUROC": 0.9992754469317587,
        "AUPRC": 0.994800087662312
    }, {
        "model": "FFNN_1",
        "run_type": "test",
        "holdout": 21,
        "Accuracy": 0.9745771194074667,
        "Balanced Accuracy": 0.9378596993024909,
        "AUROC": 0.9919694065566481,
        "AUPRC": 0.9373118771774894
    }, {
        "model": "FFNN_2",
        "run_type": "train",
        "holdout": 21,
        "Accuracy": 0.9968846572497404,
        "Balanced Accuracy": 0.9899290264906732,
        "AUROC": 0.9995745340379448,
        "AUPRC": 0.9971489562790703
    }, {
        "model": "FFNN_2",
        "run_type": "test",
        "holdout": 21,
        "Accuracy": 0.9813331998798919,
        "Balanced Accuracy": 0.9454543081047042,
        "AUROC": 0.9958256024102526,
        "AUPRC": 0.9660635811878167
    }, {
        "model": "FFNN_3",
        "run_type": "train",
        "holdout": 21,
        "Accuracy": 0.9952831959162736,
        "Balanced Accuracy": 0.9847743564494817,
        "AUROC": 0.9994564401051877,
        "AUPRC": 0.9960954614265217
    }, {
        "model": "FFNN_3",
        "run_type": "test",
        "holdout": 21,
        "Accuracy": 0.9752777499749775,
        "Balanced Accuracy": 0.9312690881436863,
        "AUROC": 0.9935703133732633,
        "AUPRC": 0.9520544494776283
    }, {
        "model": "MLP",
        "run_type": "train",
        "holdout": 22,
        "Accuracy": 0.99431981683286,
        "Balanced Accuracy": 0.9838994042363378,
        "AUROC": 0.9992656427478203,
        "AUPRC": 0.9941877941370031
    }, {
        "model": "MLP",
        "run_type": "test",
        "holdout": 22,
        "Accuracy": 0.967971174056651,
        "Balanced Accuracy": 0.9124114690953302,
        "AUROC": 0.9896365411865486,
        "AUPRC": 0.9301315011934759
    }, {
        "model": "FFNN_1",
        "run_type": "train",
        "holdout": 22,
        "Accuracy": 0.9934815519161234,
        "Balanced Accuracy": 0.9839923056156441,
        "AUROC": 0.9994041442149626,
        "AUPRC": 0.9950252536243498
    }, {
        "model": "FFNN_1",
        "run_type": "test",
        "holdout": 22,
        "Accuracy": 0.9722250025022521,
        "Balanced Accuracy": 0.9269003137610836,
        "AUROC": 0.9924037947242541,
        "AUPRC": 0.9397478033922766
    }, {
        "model": "FFNN_2",
        "run_type": "train",
        "holdout": 22,
        "Accuracy": 0.9966719631663893,
        "Balanced Accuracy": 0.9894310820375205,
        "AUROC": 0.9996118184950221,
        "AUPRC": 0.997497515852818
    }, {
        "model": "FFNN_2",
        "run_type": "test",
        "holdout": 22,
        "Accuracy": 0.9804824341907717,
        "Balanced Accuracy": 0.9425187739761158,
        "AUROC": 0.995538630152517,
        "AUPRC": 0.9692666163380048
    }, {
        "model": "FFNN_3",
        "run_type": "train",
        "holdout": 22,
        "Accuracy": 0.9952331502496028,
        "Balanced Accuracy": 0.9852654768958199,
        "AUROC": 0.9995669200769158,
        "AUPRC": 0.9963863379872391
    }, {
        "model": "FFNN_3",
        "run_type": "test",
        "holdout": 22,
        "Accuracy": 0.9743769392453208,
        "Balanced Accuracy": 0.9300047056671397,
        "AUROC": 0.9933200477262079,
        "AUPRC": 0.9539085256523243
    }, {
        "model": "MLP",
        "run_type": "train",
        "holdout": 23,
        "Accuracy": 0.9955209128329601,
        "Balanced Accuracy": 0.9865141196754073,
        "AUROC": 0.9994271119994015,
        "AUPRC": 0.9958591617117056
    }, {
        "model": "MLP",
        "run_type": "test",
        "holdout": 23,
        "Accuracy": 0.9712741467320588,
        "Balanced Accuracy": 0.9295729946628416,
        "AUROC": 0.9915658303282175,
        "AUPRC": 0.940858466155116
    }, {
        "model": "FFNN_1",
        "run_type": "train",
        "holdout": 23,
        "Accuracy": 0.9934690404994557,
        "Balanced Accuracy": 0.9860628439362001,
        "AUROC": 0.9992789145927757,
        "AUPRC": 0.9949668472013905
    }, {
        "model": "FFNN_1",
        "run_type": "test",
        "holdout": 23,
        "Accuracy": 0.9733259933940547,
        "Balanced Accuracy": 0.9356420379186043,
        "AUROC": 0.9925793699711237,
        "AUPRC": 0.9408307224961073
    }, {
        "model": "FFNN_2",
        "run_type": "train",
        "holdout": 23,
        "Accuracy": 0.9970598170830883,
        "Balanced Accuracy": 0.9919639662039623,
        "AUROC": 0.9996532569290233,
        "AUPRC": 0.9978522852122944
    }, {
        "model": "FFNN_2",
        "run_type": "test",
        "holdout": 23,
        "Accuracy": 0.980832749474527,
        "Balanced Accuracy": 0.9527245257656951,
        "AUROC": 0.9957433840233328,
        "AUPRC": 0.9688103944944406
    }, {
        "model": "FFNN_3",
        "run_type": "train",
        "holdout": 23,
        "Accuracy": 0.9954083100829507,
        "Balanced Accuracy": 0.9847978424254606,
        "AUROC": 0.9995792023679525,
        "AUPRC": 0.997011273628636
    }, {
        "model": "FFNN_3",
        "run_type": "test",
        "holdout": 23,
        "Accuracy": 0.9755279751776599,
        "Balanced Accuracy": 0.9315993248341503,
        "AUROC": 0.9935685449718121,
        "AUPRC": 0.9552416349166379
    }, {
        "model": "MLP",
        "run_type": "train",
        "holdout": 24,
        "Accuracy": 0.9942947939995246,
        "Balanced Accuracy": 0.9803911031840344,
        "AUROC": 0.9992978850092898,
        "AUPRC": 0.9957889782978425
    }, {
        "model": "MLP",
        "run_type": "test",
        "holdout": 24,
        "Accuracy": 0.9709738764888399,
        "Balanced Accuracy": 0.914486049609015,
        "AUROC": 0.991928536834218,
        "AUPRC": 0.941879818277776
    }, {
        "model": "FFNN_1",
        "run_type": "train",
        "holdout": 24,
        "Accuracy": 0.9934315062494526,
        "Balanced Accuracy": 0.9872693105305718,
        "AUROC": 0.9993866869177456,
        "AUPRC": 0.9951473377359079
    }, {
        "model": "FFNN_1",
        "run_type": "test",
        "holdout": 24,
        "Accuracy": 0.9751776598939045,
        "Balanced Accuracy": 0.9398985188090494,
        "AUROC": 0.9931915316068479,
        "AUPRC": 0.9475818967505371
    }, {
        "model": "FFNN_2",
        "run_type": "train",
        "holdout": 24,
        "Accuracy": 0.9968471229997372,
        "Balanced Accuracy": 0.9901439070877502,
        "AUROC": 0.999574940146574,
        "AUPRC": 0.9974451273103555
    }, {
        "model": "FFNN_2",
        "run_type": "test",
        "holdout": 24,
        "Accuracy": 0.9830847762986687,
        "Balanced Accuracy": 0.9507871805729704,
        "AUROC": 0.9955404722373621,
        "AUPRC": 0.9680045926764499
    }, {
        "model": "FFNN_3",
        "run_type": "train",
        "holdout": 24,
        "Accuracy": 0.9947452049995621,
        "Balanced Accuracy": 0.9849425115234667,
        "AUROC": 0.9995056260784811,
        "AUPRC": 0.9964285483532903
    }, {
        "model": "FFNN_3",
        "run_type": "test",
        "holdout": 24,
        "Accuracy": 0.975427885096587,
        "Balanced Accuracy": 0.931165108594463,
        "AUROC": 0.9940352433076014,
        "AUPRC": 0.9553727806624457
    }, {
        "model": "MLP",
        "run_type": "train",
        "holdout": 25,
        "Accuracy": 0.995483378582957,
        "Balanced Accuracy": 0.9887593906478971,
        "AUROC": 0.9995002368864644,
        "AUPRC": 0.9960600408573211
    }, {
        "model": "MLP",
        "run_type": "test",
        "holdout": 25,
        "Accuracy": 0.9718246421779602,
        "Balanced Accuracy": 0.9308282281179907,
        "AUROC": 0.9927140754955631,
        "AUPRC": 0.947663770293597
    }, {
        "model": "FFNN_1",
        "run_type": "train",
        "holdout": 25,
        "Accuracy": 0.9940445656661704,
        "Balanced Accuracy": 0.9841688200787845,
        "AUROC": 0.9993910274436236,
        "AUPRC": 0.994061094837154
    }, {
        "model": "FFNN_1",
        "run_type": "test",
        "holdout": 25,
        "Accuracy": 0.9720248223401061,
        "Balanced Accuracy": 0.9233883176010691,
        "AUROC": 0.9922765189420234,
        "AUPRC": 0.9395566152643787
    }, {
        "model": "FFNN_2",
        "run_type": "train",
        "holdout": 25,
        "Accuracy": 0.99715990841643,
        "Balanced Accuracy": 0.9904151047414035,
        "AUROC": 0.9997680490220558,
        "AUPRC": 0.998624063138951
    }, {
        "model": "FFNN_2",
        "run_type": "test",
        "holdout": 25,
        "Accuracy": 0.9832849564608147,
        "Balanced Accuracy": 0.9533550468470422,
        "AUROC": 0.9965941324881947,
        "AUPRC": 0.9766077742015535
    }, {
        "model": "FFNN_3",
        "run_type": "train",
        "holdout": 25,
        "Accuracy": 0.9958712324996559,
        "Balanced Accuracy": 0.9875620227292782,
        "AUROC": 0.9996013318336334,
        "AUPRC": 0.9969573251799277
    }, {
        "model": "FFNN_3",
        "run_type": "test",
        "holdout": 25,
        "Accuracy": 0.9767791011910719,
        "Balanced Accuracy": 0.9357052459899224,
        "AUROC": 0.9941642260884554,
        "AUPRC": 0.9583025528448262
    }, {
        "model": "MLP",
        "run_type": "train",
        "holdout": 26,
        "Accuracy": 0.9958086754163173,
        "Balanced Accuracy": 0.9871489235042885,
        "AUROC": 0.9995814209954353,
        "AUPRC": 0.9971149438728251
    }, {
        "model": "MLP",
        "run_type": "test",
        "holdout": 26,
        "Accuracy": 0.973976578921029,
        "Balanced Accuracy": 0.9273237108224475,
        "AUROC": 0.9933611262182536,
        "AUPRC": 0.9518696746640927
    }, {
        "model": "FFNN_1",
        "run_type": "train",
        "holdout": 26,
        "Accuracy": 0.9939694971661641,
        "Balanced Accuracy": 0.9861095694592923,
        "AUROC": 0.9993844997656008,
        "AUPRC": 0.9945912674760629
    }, {
        "model": "FFNN_1",
        "run_type": "test",
        "holdout": 26,
        "Accuracy": 0.9751776598939045,
        "Balanced Accuracy": 0.9323454797215072,
        "AUROC": 0.9935460224144392,
        "AUPRC": 0.9428682075537765
    }, {
        "model": "FFNN_2",
        "run_type": "train",
        "holdout": 26,
        "Accuracy": 0.9970347942497529,
        "Balanced Accuracy": 0.9917609518093076,
        "AUROC": 0.9996252116351825,
        "AUPRC": 0.9978529917040421
    }, {
        "model": "FFNN_2",
        "run_type": "test",
        "holdout": 26,
        "Accuracy": 0.9833350015013512,
        "Balanced Accuracy": 0.9550827627843943,
        "AUROC": 0.9966784631324033,
        "AUPRC": 0.97166218403189
    }, {
        "model": "FFNN_3",
        "run_type": "train",
        "holdout": 26,
        "Accuracy": 0.9949954333329163,
        "Balanced Accuracy": 0.9855561040453071,
        "AUROC": 0.9995486536332053,
        "AUPRC": 0.9962248837838121
    }, {
        "model": "FFNN_3",
        "run_type": "test",
        "holdout": 26,
        "Accuracy": 0.9761285156640976,
        "Balanced Accuracy": 0.9383587937704227,
        "AUROC": 0.9940408186843993,
        "AUPRC": 0.9576041008971005
    }, {
        "model": "MLP",
        "run_type": "train",
        "holdout": 27,
        "Accuracy": 0.9953832872496152,
        "Balanced Accuracy": 0.9866252184062188,
        "AUROC": 0.9994836340295201,
        "AUPRC": 0.9966197161619614
    }, {
        "model": "MLP",
        "run_type": "test",
        "holdout": 27,
        "Accuracy": 0.9727254529076168,
        "Balanced Accuracy": 0.9296378728910861,
        "AUROC": 0.9929426782248403,
        "AUPRC": 0.947650607520781
    }, {
        "model": "FFNN_1",
        "run_type": "train",
        "holdout": 27,
        "Accuracy": 0.9938944286661578,
        "Balanced Accuracy": 0.9842728483739157,
        "AUROC": 0.9993344647258727,
        "AUPRC": 0.9938392409418098
    }, {
        "model": "FFNN_1",
        "run_type": "test",
        "holdout": 27,
        "Accuracy": 0.9749274346912221,
        "Balanced Accuracy": 0.9295605053275918,
        "AUROC": 0.993534048862946,
        "AUPRC": 0.9449687870687751
    }, {
        "model": "FFNN_2",
        "run_type": "train",
        "holdout": 27,
        "Accuracy": 0.996947214333079,
        "Balanced Accuracy": 0.9902949073348393,
        "AUROC": 0.9997499230658292,
        "AUPRC": 0.9982912911913372
    }, {
        "model": "FFNN_2",
        "run_type": "test",
        "holdout": 27,
        "Accuracy": 0.9850365328795916,
        "Balanced Accuracy": 0.9562331816118571,
        "AUROC": 0.9968937291674019,
        "AUPRC": 0.9792509370988515
    }, {
        "model": "FFNN_3",
        "run_type": "train",
        "holdout": 27,
        "Accuracy": 0.9954458443329538,
        "Balanced Accuracy": 0.9856689845873254,
        "AUROC": 0.9995387104971649,
        "AUPRC": 0.996054366563582
    }, {
        "model": "FFNN_3",
        "run_type": "test",
        "holdout": 27,
        "Accuracy": 0.976478830947853,
        "Balanced Accuracy": 0.9338361193392948,
        "AUROC": 0.9947920208842317,
        "AUPRC": 0.9613724613700246
    }, {
        "model": "MLP",
        "run_type": "train",
        "holdout": 28,
        "Accuracy": 0.9954708671662892,
        "Balanced Accuracy": 0.9845971026997442,
        "AUROC": 0.9994856315619458,
        "AUPRC": 0.9963013208206454
    }, {
        "model": "MLP",
        "run_type": "test",
        "holdout": 28,
        "Accuracy": 0.9729256330697628,
        "Balanced Accuracy": 0.917288486967262,
        "AUROC": 0.9928465705181885,
        "AUPRC": 0.9487193174573688
    }, {
        "model": "FFNN_1",
        "run_type": "train",
        "holdout": 28,
        "Accuracy": 0.9940820999161735,
        "Balanced Accuracy": 0.9866926055694736,
        "AUROC": 0.9993486247895125,
        "AUPRC": 0.9942455159547782
    }, {
        "model": "FFNN_1",
        "run_type": "test",
        "holdout": 28,
        "Accuracy": 0.9755780202181964,
        "Balanced Accuracy": 0.9371035603152735,
        "AUROC": 0.9938715310871343,
        "AUPRC": 0.9434755282087904
    }, {
        "model": "FFNN_2",
        "run_type": "train",
        "holdout": 28,
        "Accuracy": 0.9969972599997498,
        "Balanced Accuracy": 0.990039878792619,
        "AUROC": 0.9997066183745931,
        "AUPRC": 0.9979039560706451
    }, {
        "model": "FFNN_2",
        "run_type": "test",
        "holdout": 28,
        "Accuracy": 0.9843359023120809,
        "Balanced Accuracy": 0.954704275751554,
        "AUROC": 0.9967689094982978,
        "AUPRC": 0.9762549359258421
    }, {
        "model": "FFNN_3",
        "run_type": "train",
        "holdout": 28,
        "Accuracy": 0.9950830132495903,
        "Balanced Accuracy": 0.9856055970950689,
        "AUROC": 0.9994557660723402,
        "AUPRC": 0.9960210579141704
    }, {
        "model": "FFNN_3",
        "run_type": "test",
        "holdout": 28,
        "Accuracy": 0.9781803623260935,
        "Balanced Accuracy": 0.9391407096649058,
        "AUROC": 0.9954950095833849,
        "AUPRC": 0.9643459517988786
    }, {
        "model": "MLP",
        "run_type": "train",
        "holdout": 29,
        "Accuracy": 0.9961589950830132,
        "Balanced Accuracy": 0.9910299294075726,
        "AUROC": 0.9996877531317693,
        "AUPRC": 0.9974490458531022
    }, {
        "model": "MLP",
        "run_type": "test",
        "holdout": 29,
        "Accuracy": 0.975427885096587,
        "Balanced Accuracy": 0.9413617113626449,
        "AUROC": 0.9942566741865483,
        "AUPRC": 0.9566689840607022
    }, {
        "model": "FFNN_1",
        "run_type": "train",
        "holdout": 29,
        "Accuracy": 0.99268082124939,
        "Balanced Accuracy": 0.9864673373431686,
        "AUROC": 0.9990331797198655,
        "AUPRC": 0.9916299682947194
    }, {
        "model": "FFNN_1",
        "run_type": "test",
        "holdout": 29,
        "Accuracy": 0.9753277950155139,
        "Balanced Accuracy": 0.9435710588035974,
        "AUROC": 0.9940023805139647,
        "AUPRC": 0.9391051045320179
    }, {
        "model": "FFNN_2",
        "run_type": "train",
        "holdout": 29,
        "Accuracy": 0.9973726024997811,
        "Balanced Accuracy": 0.9918574168110271,
        "AUROC": 0.9997943240200571,
        "AUPRC": 0.998692035333784
    }, {
        "model": "FFNN_2",
        "run_type": "test",
        "holdout": 29,
        "Accuracy": 0.9852367130417375,
        "Balanced Accuracy": 0.9614446115665687,
        "AUROC": 0.9972566444430183,
        "AUPRC": 0.9740380563826511
    }, {
        "model": "FFNN_3",
        "run_type": "train",
        "holdout": 29,
        "Accuracy": 0.9959713238329976,
        "Balanced Accuracy": 0.9877130229763672,
        "AUROC": 0.9996582169816758,
        "AUPRC": 0.9977401354768574
    }, {
        "model": "FFNN_3",
        "run_type": "test",
        "holdout": 29,
        "Accuracy": 0.9799319387448704,
        "Balanced Accuracy": 0.9429629743156637,
        "AUROC": 0.9949860292601179,
        "AUPRC": 0.9667287451587077
    }, {
        "model": "MLP",
        "run_type": "train",
        "holdout": 30,
        "Accuracy": 0.9952831959162736,
        "Balanced Accuracy": 0.9879852063454835,
        "AUROC": 0.999590478215865,
        "AUPRC": 0.9968044727795036
    }, {
        "model": "MLP",
        "run_type": "test",
        "holdout": 30,
        "Accuracy": 0.9756280652587329,
        "Balanced Accuracy": 0.9392089282070029,
        "AUROC": 0.9935645169462841,
        "AUPRC": 0.9541953567916719
    }, {
        "model": "FFNN_1",
        "run_type": "train",
        "holdout": 30,
        "Accuracy": 0.9943323282495277,
        "Balanced Accuracy": 0.988156128946138,
        "AUROC": 0.999570720915901,
        "AUPRC": 0.9959699283553681
    }, {
        "model": "FFNN_1",
        "run_type": "test",
        "holdout": 30,
        "Accuracy": 0.9780302272044841,
        "Balanced Accuracy": 0.9445318165754085,
        "AUROC": 0.994360064268621,
        "AUPRC": 0.9470731017364009
    }, {
        "model": "FFNN_2",
        "run_type": "train",
        "holdout": 30,
        "Accuracy": 0.9973100454164425,
        "Balanced Accuracy": 0.9918692830134495,
        "AUROC": 0.9996450825534396,
        "AUPRC": 0.9972052307104498
    }, {
        "model": "FFNN_2",
        "run_type": "test",
        "holdout": 30,
        "Accuracy": 0.9855870283254929,
        "Balanced Accuracy": 0.9620202385195317,
        "AUROC": 0.9966327794282448,
        "AUPRC": 0.972109247497717
    }, {
        "model": "FFNN_3",
        "run_type": "train",
        "holdout": 30,
        "Accuracy": 0.9956710498329726,
        "Balanced Accuracy": 0.9870239303309822,
        "AUROC": 0.9995818601147849,
        "AUPRC": 0.9969833487522737
    }, {
        "model": "FFNN_3",
        "run_type": "test",
        "holdout": 30,
        "Accuracy": 0.9792313081773596,
        "Balanced Accuracy": 0.9438888061588118,
        "AUROC": 0.9958170796977027,
        "AUPRC": 0.9682762453192643
    }, {
        "model": "MLP",
        "run_type": "train",
        "holdout": 31,
        "Accuracy": 0.9959838352496653,
        "Balanced Accuracy": 0.9869173809380472,
        "AUROC": 0.9995681798581267,
        "AUPRC": 0.9971906153652521
    }, {
        "model": "MLP",
        "run_type": "test",
        "holdout": 31,
        "Accuracy": 0.9783805424882395,
        "Balanced Accuracy": 0.9417085759389776,
        "AUROC": 0.9946194912176395,
        "AUPRC": 0.9605466511183494
    }, {
        "model": "FFNN_1",
        "run_type": "train",
        "holdout": 31,
        "Accuracy": 0.9938443829994871,
        "Balanced Accuracy": 0.9873137613847257,
        "AUROC": 0.9992450494321719,
        "AUPRC": 0.993414823481827
    }, {
        "model": "FFNN_1",
        "run_type": "test",
        "holdout": 31,
        "Accuracy": 0.9774296867180462,
        "Balanced Accuracy": 0.9464583425898097,
        "AUROC": 0.9944659718666486,
        "AUPRC": 0.9496804203666317
    }, {
        "model": "FFNN_2",
        "run_type": "train",
        "holdout": 31,
        "Accuracy": 0.9974977166664581,
        "Balanced Accuracy": 0.9924947417377123,
        "AUROC": 0.9997846050498388,
        "AUPRC": 0.9981647277918937
    }, {
        "model": "FFNN_2",
        "run_type": "test",
        "holdout": 31,
        "Accuracy": 0.9855870283254929,
        "Balanced Accuracy": 0.9650414541545485,
        "AUROC": 0.9972326973400317,
        "AUPRC": 0.977546196684033
    }, {
        "model": "FFNN_3",
        "run_type": "train",
        "holdout": 31,
        "Accuracy": 0.9959212781663268,
        "Balanced Accuracy": 0.9872125574254107,
        "AUROC": 0.9997307215742729,
        "AUPRC": 0.998063141205376
    }, {
        "model": "FFNN_3",
        "run_type": "test",
        "holdout": 31,
        "Accuracy": 0.9801321189070163,
        "Balanced Accuracy": 0.9434537548406613,
        "AUROC": 0.9961490479479211,
        "AUPRC": 0.9727647846115121
    }, {
        "model": "MLP",
        "run_type": "train",
        "holdout": 32,
        "Accuracy": 0.9961464836663455,
        "Balanced Accuracy": 0.9877647906950671,
        "AUROC": 0.999607463383012,
        "AUPRC": 0.9972767248271511
    }, {
        "model": "MLP",
        "run_type": "test",
        "holdout": 32,
        "Accuracy": 0.9791812631368232,
        "Balanced Accuracy": 0.9414057863127054,
        "AUROC": 0.9954367260188861,
        "AUPRC": 0.9659470072882613
    }, {
        "model": "FFNN_1",
        "run_type": "train",
        "holdout": 32,
        "Accuracy": 0.9949704104995809,
        "Balanced Accuracy": 0.988044537357595,
        "AUROC": 0.9994443981014874,
        "AUPRC": 0.9943074778918403
    }, {
        "model": "FFNN_1",
        "run_type": "test",
        "holdout": 32,
        "Accuracy": 0.9786808127314583,
        "Balanced Accuracy": 0.9430112246580398,
        "AUROC": 0.9944574245929674,
        "AUPRC": 0.9544550312730882
    }, {
        "model": "FFNN_2",
        "run_type": "train",
        "holdout": 32,
        "Accuracy": 0.997247488333104,
        "Balanced Accuracy": 0.9909367815994008,
        "AUROC": 0.9997441461897714,
        "AUPRC": 0.9985856790788491
    }, {
        "model": "FFNN_2",
        "run_type": "test",
        "holdout": 32,
        "Accuracy": 0.9867380642578321,
        "Balanced Accuracy": 0.9641813356181079,
        "AUROC": 0.9974456791898225,
        "AUPRC": 0.9814000458026247
    }, {
        "model": "FFNN_3",
        "run_type": "train",
        "holdout": 32,
        "Accuracy": 0.9958837439163236,
        "Balanced Accuracy": 0.9862941968827225,
        "AUROC": 0.9995871410623468,
        "AUPRC": 0.9978358706005619
    }, {
        "model": "FFNN_3",
        "run_type": "test",
        "holdout": 32,
        "Accuracy": 0.9799819837854069,
        "Balanced Accuracy": 0.9401588668004904,
        "AUROC": 0.9956655006760821,
        "AUPRC": 0.9671213202774921
    }, {
        "model": "MLP",
        "run_type": "train",
        "holdout": 33,
        "Accuracy": 0.9963466663330289,
        "Balanced Accuracy": 0.9885861933783043,
        "AUROC": 0.9996830157095563,
        "AUPRC": 0.9977979097742888
    }, {
        "model": "MLP",
        "run_type": "test",
        "holdout": 33,
        "Accuracy": 0.9780802722450205,
        "Balanced Accuracy": 0.9398394492883498,
        "AUROC": 0.9944711911070433,
        "AUPRC": 0.9610261055950599
    }, {
        "model": "FFNN_1",
        "run_type": "train",
        "holdout": 33,
        "Accuracy": 0.9943323282495277,
        "Balanced Accuracy": 0.9910364501763748,
        "AUROC": 0.9995043087204328,
        "AUPRC": 0.9954819885598102
    }, {
        "model": "FFNN_1",
        "run_type": "test",
        "holdout": 33,
        "Accuracy": 0.9768291462316084,
        "Balanced Accuracy": 0.9417759594026114,
        "AUROC": 0.9944557175943444,
        "AUPRC": 0.952261581146494
    }, {
        "model": "FFNN_2",
        "run_type": "train",
        "holdout": 33,
        "Accuracy": 0.9976853879164738,
        "Balanced Accuracy": 0.9919869593222097,
        "AUROC": 0.9998066754032993,
        "AUPRC": 0.9984886668915952
    }, {
        "model": "FFNN_2",
        "run_type": "test",
        "holdout": 33,
        "Accuracy": 0.9860374336903213,
        "Balanced Accuracy": 0.9611418219402965,
        "AUROC": 0.9978126716132295,
        "AUPRC": 0.98525713086219
    }, {
        "model": "FFNN_3",
        "run_type": "train",
        "holdout": 33,
        "Accuracy": 0.9958211868329852,
        "Balanced Accuracy": 0.9871559939399688,
        "AUROC": 0.9995051493422644,
        "AUPRC": 0.9966110193132828
    }, {
        "model": "FFNN_3",
        "run_type": "test",
        "holdout": 33,
        "Accuracy": 0.9783805424882395,
        "Balanced Accuracy": 0.9435968357108631,
        "AUROC": 0.9945129327496333,
        "AUPRC": 0.961620638196367
    }, {
        "model": "MLP",
        "run_type": "train",
        "holdout": 34,
        "Accuracy": 0.995608492749634,
        "Balanced Accuracy": 0.9860914289169335,
        "AUROC": 0.9995837202304909,
        "AUPRC": 0.9964807068012064
    }, {
        "model": "MLP",
        "run_type": "test",
        "holdout": 34,
        "Accuracy": 0.9751276148533681,
        "Balanced Accuracy": 0.9300512858525894,
        "AUROC": 0.9939454846533823,
        "AUPRC": 0.9574804399473397
    }, {
        "model": "FFNN_1",
        "run_type": "train",
        "holdout": 34,
        "Accuracy": 0.9947326935828944,
        "Balanced Accuracy": 0.9896100607893183,
        "AUROC": 0.9994164641228668,
        "AUPRC": 0.9933954007319838
    }, {
        "model": "FFNN_1",
        "run_type": "test",
        "holdout": 34,
        "Accuracy": 0.9780802722450205,
        "Balanced Accuracy": 0.9428606649233666,
        "AUROC": 0.9945600287188394,
        "AUPRC": 0.9519138027165068
    }, {
        "model": "FFNN_2",
        "run_type": "train",
        "holdout": 34,
        "Accuracy": 0.9976603650831384,
        "Balanced Accuracy": 0.9928227493056733,
        "AUROC": 0.9998198320945793,
        "AUPRC": 0.9988428034389758
    }, {
        "model": "FFNN_2",
        "run_type": "test",
        "holdout": 34,
        "Accuracy": 0.986838154338905,
        "Balanced Accuracy": 0.9632937700174755,
        "AUROC": 0.9966785245352315,
        "AUPRC": 0.9806103635400532
    }, {
        "model": "FFNN_3",
        "run_type": "train",
        "holdout": 34,
        "Accuracy": 0.9960088580830008,
        "Balanced Accuracy": 0.9874509239984666,
        "AUROC": 0.9996959758718964,
        "AUPRC": 0.9978091484932861
    }, {
        "model": "FFNN_3",
        "run_type": "test",
        "holdout": 34,
        "Accuracy": 0.979381443298969,
        "Balanced Accuracy": 0.9418965668377031,
        "AUROC": 0.9959987215439954,
        "AUPRC": 0.9717616713179899
    }, {
        "model": "MLP",
        "run_type": "train",
        "holdout": 35,
        "Accuracy": 0.9964342462497029,
        "Balanced Accuracy": 0.9891078702363016,
        "AUROC": 0.9997295784821201,
        "AUPRC": 0.9978353570923397
    }, {
        "model": "MLP",
        "run_type": "test",
        "holdout": 35,
        "Accuracy": 0.9815834250825743,
        "Balanced Accuracy": 0.9486169344529967,
        "AUROC": 0.9961284288782218,
        "AUPRC": 0.9701819466217942
    }, {
        "model": "FFNN_1",
        "run_type": "train",
        "holdout": 35,
        "Accuracy": 0.9936066660828006,
        "Balanced Accuracy": 0.988123790723272,
        "AUROC": 0.9993396458735824,
        "AUPRC": 0.9930587932684948
    }, {
        "model": "FFNN_1",
        "run_type": "test",
        "holdout": 35,
        "Accuracy": 0.9780802722450205,
        "Balanced Accuracy": 0.9538125716003029,
        "AUROC": 0.9945779460640998,
        "AUPRC": 0.9387933741284495
    }, {
        "model": "FFNN_2",
        "run_type": "train",
        "holdout": 35,
        "Accuracy": 0.9974601824164551,
        "Balanced Accuracy": 0.992426312049848,
        "AUROC": 0.9997246606524819,
        "AUPRC": 0.9981020758006999
    }, {
        "model": "FFNN_2",
        "run_type": "test",
        "holdout": 35,
        "Accuracy": 0.9867881092983686,
        "Balanced Accuracy": 0.9660978775326488,
        "AUROC": 0.9971361598135831,
        "AUPRC": 0.9800384043613863
    }, {
        "model": "FFNN_3",
        "run_type": "train",
        "holdout": 35,
        "Accuracy": 0.9959838352496653,
        "Balanced Accuracy": 0.9867285074147528,
        "AUROC": 0.9996380505023182,
        "AUPRC": 0.9969861085868872
    }, {
        "model": "FFNN_3",
        "run_type": "test",
        "holdout": 35,
        "Accuracy": 0.9804323891502352,
        "Balanced Accuracy": 0.9396581021756324,
        "AUROC": 0.9961717424332126,
        "AUPRC": 0.9722288818801296
    }, {
        "model": "MLP",
        "run_type": "train",
        "holdout": 36,
        "Accuracy": 0.9955334242496278,
        "Balanced Accuracy": 0.9853407305904986,
        "AUROC": 0.9996475145990679,
        "AUPRC": 0.99756927331272
    }, {
        "model": "MLP",
        "run_type": "test",
        "holdout": 36,
        "Accuracy": 0.9776799119207287,
        "Balanced Accuracy": 0.9392355401927317,
        "AUROC": 0.9952138214720632,
        "AUPRC": 0.9663334577009614
    }, {
        "model": "FFNN_1",
        "run_type": "train",
        "holdout": 36,
        "Accuracy": 0.99492036483291,
        "Balanced Accuracy": 0.9888661864696979,
        "AUROC": 0.9995986333991689,
        "AUPRC": 0.9959386544067473
    }, {
        "model": "FFNN_1",
        "run_type": "test",
        "holdout": 36,
        "Accuracy": 0.9788309478530678,
        "Balanced Accuracy": 0.95159324005949,
        "AUROC": 0.9951088226358923,
        "AUPRC": 0.958860857981427
    }, {
        "model": "FFNN_2",
        "run_type": "train",
        "holdout": 36,
        "Accuracy": 0.9976228308331352,
        "Balanced Accuracy": 0.9936042504726329,
        "AUROC": 0.9998265708876738,
        "AUPRC": 0.9984110117033036
    }, {
        "model": "FFNN_2",
        "run_type": "test",
        "holdout": 36,
        "Accuracy": 0.9875888299469523,
        "Balanced Accuracy": 0.9654174359519994,
        "AUROC": 0.9980197465109502,
        "AUPRC": 0.9848579943609995
    }, {
        "model": "FFNN_3",
        "run_type": "train",
        "holdout": 36,
        "Accuracy": 0.9962340635830195,
        "Balanced Accuracy": 0.9877670653640054,
        "AUROC": 0.9997507690614994,
        "AUPRC": 0.9979254541826816
    }, {
        "model": "FFNN_3",
        "run_type": "test",
        "holdout": 36,
        "Accuracy": 0.9817335602041838,
        "Balanced Accuracy": 0.9494570847897164,
        "AUROC": 0.9964417675103734,
        "AUPRC": 0.9700005835357672
    }, {
        "model": "MLP",
        "run_type": "train",
        "holdout": 37,
        "Accuracy": 0.9964467576663706,
        "Balanced Accuracy": 0.9882177914363344,
        "AUROC": 0.9996810911077916,
        "AUPRC": 0.9977164979597415
    }, {
        "model": "MLP",
        "run_type": "test",
        "holdout": 37,
        "Accuracy": 0.9798818937043339,
        "Balanced Accuracy": 0.9455782558536483,
        "AUROC": 0.995605068012597,
        "AUPRC": 0.9641425457224915
    }, {
        "model": "FFNN_1",
        "run_type": "train",
        "holdout": 37,
        "Accuracy": 0.9952331502496028,
        "Balanced Accuracy": 0.989798441454881,
        "AUROC": 0.9995353602928969,
        "AUPRC": 0.994542544265419
    }, {
        "model": "FFNN_1",
        "run_type": "test",
        "holdout": 37,
        "Accuracy": 0.981133019717746,
        "Balanced Accuracy": 0.9528942186216258,
        "AUROC": 0.9958593248434836,
        "AUPRC": 0.9633357551997246
    }, {
        "model": "FFNN_2",
        "run_type": "train",
        "holdout": 37,
        "Accuracy": 0.9975352509164612,
        "Balanced Accuracy": 0.9923270795214587,
        "AUROC": 0.9997245961664235,
        "AUPRC": 0.9980893741455152
    }, {
        "model": "FFNN_2",
        "run_type": "test",
        "holdout": 37,
        "Accuracy": 0.9876889200280252,
        "Balanced Accuracy": 0.9686840418495151,
        "AUROC": 0.9973119806717651,
        "AUPRC": 0.9771120064729204
    }, {
        "model": "FFNN_3",
        "run_type": "train",
        "holdout": 37,
        "Accuracy": 0.9962465749996872,
        "Balanced Accuracy": 0.9874908255147442,
        "AUROC": 0.9996099714300661,
        "AUPRC": 0.9967772170679194
    }, {
        "model": "FFNN_3",
        "run_type": "test",
        "holdout": 37,
        "Accuracy": 0.9805324792313082,
        "Balanced Accuracy": 0.9451906197994107,
        "AUROC": 0.9959970636676347,
        "AUPRC": 0.9689604369119457
    }, {
        "model": "MLP",
        "run_type": "train",
        "holdout": 38,
        "Accuracy": 0.9964342462497029,
        "Balanced Accuracy": 0.9879746290965363,
        "AUROC": 0.999659587310415,
        "AUPRC": 0.9976868295439666
    }, {
        "model": "MLP",
        "run_type": "test",
        "holdout": 38,
        "Accuracy": 0.9807326593934541,
        "Balanced Accuracy": 0.9466255302103511,
        "AUROC": 0.9961959351475118,
        "AUPRC": 0.9707358252613713
    }, {
        "model": "FFNN_1",
        "run_type": "train",
        "holdout": 38,
        "Accuracy": 0.995570958499631,
        "Balanced Accuracy": 0.9881006079853055,
        "AUROC": 0.9996325868442576,
        "AUPRC": 0.9964246327199583
    }, {
        "model": "FFNN_1",
        "run_type": "test",
        "holdout": 38,
        "Accuracy": 0.980832749474527,
        "Balanced Accuracy": 0.9502697880622439,
        "AUROC": 0.9959156312369155,
        "AUPRC": 0.9591101325034215
    }, {
        "model": "FFNN_2",
        "run_type": "train",
        "holdout": 38,
        "Accuracy": 0.9976978993331415,
        "Balanced Accuracy": 0.9921356849003606,
        "AUROC": 0.9998725947410362,
        "AUPRC": 0.9988133807310237
    }, {
        "model": "FFNN_2",
        "run_type": "test",
        "holdout": 38,
        "Accuracy": 0.9885396857171455,
        "Balanced Accuracy": 0.9642553628677498,
        "AUROC": 0.9977459267390084,
        "AUPRC": 0.9856800615412845
    }, {
        "model": "FFNN_3",
        "run_type": "train",
        "holdout": 38,
        "Accuracy": 0.9961840179163487,
        "Balanced Accuracy": 0.9876443468596372,
        "AUROC": 0.9997280346551762,
        "AUPRC": 0.9980691124617054
    }, {
        "model": "FFNN_3",
        "run_type": "test",
        "holdout": 38,
        "Accuracy": 0.9809828845961365,
        "Balanced Accuracy": 0.9490328526498895,
        "AUROC": 0.9960271387728723,
        "AUPRC": 0.9678056855165241
    }, {
        "model": "MLP",
        "run_type": "train",
        "holdout": 39,
        "Accuracy": 0.9966719631663893,
        "Balanced Accuracy": 0.9923114032677574,
        "AUROC": 0.9997221940607511,
        "AUPRC": 0.9979146325401441
    }, {
        "model": "MLP",
        "run_type": "test",
        "holdout": 39,
        "Accuracy": 0.9794314883395056,
        "Balanced Accuracy": 0.9447572386381864,
        "AUROC": 0.996402862678445,
        "AUPRC": 0.9743127723820003
    }, {
        "model": "FFNN_1",
        "run_type": "train",
        "holdout": 39,
        "Accuracy": 0.9950705018329226,
        "Balanced Accuracy": 0.9871095148457424,
        "AUROC": 0.9996590760280955,
        "AUPRC": 0.9967574519516207
    }, {
        "model": "FFNN_1",
        "run_type": "test",
        "holdout": 39,
        "Accuracy": 0.979581623461115,
        "Balanced Accuracy": 0.9480521266783573,
        "AUROC": 0.9954306102972003,
        "AUPRC": 0.9557815038520687
    }, {
        "model": "FFNN_2",
        "run_type": "train",
        "holdout": 39,
        "Accuracy": 0.9973100454164425,
        "Balanced Accuracy": 0.9933802711998032,
        "AUROC": 0.9997674003230168,
        "AUPRC": 0.9983183678569931
    }, {
        "model": "FFNN_2",
        "run_type": "test",
        "holdout": 39,
        "Accuracy": 0.9877890101090981,
        "Balanced Accuracy": 0.9683629541804482,
        "AUROC": 0.9980365094830405,
        "AUPRC": 0.9860129094517008
    }, {
        "model": "FFNN_3",
        "run_type": "train",
        "holdout": 39,
        "Accuracy": 0.9962465749996872,
        "Balanced Accuracy": 0.9891906872243922,
        "AUROC": 0.9997619765848973,
        "AUPRC": 0.9981424780139195
    }, {
        "model": "FFNN_3",
        "run_type": "test",
        "holdout": 39,
        "Accuracy": 0.9808827945150635,
        "Balanced Accuracy": 0.9476545065242592,
        "AUROC": 0.9960113705265982,
        "AUPRC": 0.9698935908017987
    }, {
        "model": "MLP",
        "run_type": "train",
        "holdout": 40,
        "Accuracy": 0.9966344289163862,
        "Balanced Accuracy": 0.9885599398756558,
        "AUROC": 0.9997659117698373,
        "AUPRC": 0.9978953485355619
    }, {
        "model": "MLP",
        "run_type": "test",
        "holdout": 40,
        "Accuracy": 0.9810829746772095,
        "Balanced Accuracy": 0.9492782429123883,
        "AUROC": 0.9958747615144856,
        "AUPRC": 0.966948052393352
    }, {
        "model": "FFNN_1",
        "run_type": "train",
        "holdout": 40,
        "Accuracy": 0.9955584470829631,
        "Balanced Accuracy": 0.9886129397386844,
        "AUROC": 0.9995450401108656,
        "AUPRC": 0.9958214685607129
    }, {
        "model": "FFNN_1",
        "run_type": "test",
        "holdout": 40,
        "Accuracy": 0.982484235812231,
        "Balanced Accuracy": 0.9546019663592571,
        "AUROC": 0.9964481165628063,
        "AUPRC": 0.966488798954388
    }, {
        "model": "FFNN_2",
        "run_type": "train",
        "holdout": 40,
        "Accuracy": 0.9976228308331352,
        "Balanced Accuracy": 0.9917155152396908,
        "AUROC": 0.9998340305427773,
        "AUPRC": 0.9989527369434373
    }, {
        "model": "FFNN_2",
        "run_type": "test",
        "holdout": 40,
        "Accuracy": 0.9890401361225103,
        "Balanced Accuracy": 0.9694476597012035,
        "AUROC": 0.9982459176882317,
        "AUPRC": 0.9870824756198661
    }, {
        "model": "FFNN_3",
        "run_type": "train",
        "holdout": 40,
        "Accuracy": 0.9960463923330038,
        "Balanced Accuracy": 0.987188825020566,
        "AUROC": 0.9996349390500041,
        "AUPRC": 0.9973219991264575
    }, {
        "model": "FFNN_3",
        "run_type": "test",
        "holdout": 40,
        "Accuracy": 0.9833350015013512,
        "Balanced Accuracy": 0.957726326465034,
        "AUROC": 0.9966332952120014,
        "AUPRC": 0.9743977994055959
    }, {
        "model": "MLP",
        "run_type": "train",
        "holdout": 41,
        "Accuracy": 0.9966469403330539,
        "Balanced Accuracy": 0.9885197919305125,
        "AUROC": 0.9997897869652395,
        "AUPRC": 0.9983190125850409
    }, {
        "model": "MLP",
        "run_type": "test",
        "holdout": 41,
        "Accuracy": 0.9815333800420378,
        "Balanced Accuracy": 0.9468892185156446,
        "AUROC": 0.996346654529538,
        "AUPRC": 0.9743211446830016
    }, {
        "model": "FFNN_1",
        "run_type": "train",
        "holdout": 41,
        "Accuracy": 0.9955584470829631,
        "Balanced Accuracy": 0.9898878360209202,
        "AUROC": 0.9996713260761031,
        "AUPRC": 0.9967740759281566
    }, {
        "model": "FFNN_1",
        "run_type": "test",
        "holdout": 41,
        "Accuracy": 0.9811830647582824,
        "Balanced Accuracy": 0.951600718923961,
        "AUROC": 0.9962196243586199,
        "AUPRC": 0.9567563509109673
    }, {
        "model": "FFNN_2",
        "run_type": "train",
        "holdout": 41,
        "Accuracy": 0.9975727851664644,
        "Balanced Accuracy": 0.9939537157765004,
        "AUROC": 0.9997662173109231,
        "AUPRC": 0.9982120092325161
    }, {
        "model": "FFNN_2",
        "run_type": "test",
        "holdout": 41,
        "Accuracy": 0.9875888299469523,
        "Balanced Accuracy": 0.9654174359519994,
        "AUROC": 0.9977787526909483,
        "AUPRC": 0.9852844196214418
    }, {
        "model": "FFNN_3",
        "run_type": "train",
        "holdout": 41,
        "Accuracy": 0.9961840179163487,
        "Balanced Accuracy": 0.9877387836212843,
        "AUROC": 0.9996817889390658,
        "AUPRC": 0.9974129174876604
    }, {
        "model": "FFNN_3",
        "run_type": "test",
        "holdout": 41,
        "Accuracy": 0.982684415974377,
        "Balanced Accuracy": 0.9511274013632951,
        "AUROC": 0.9971168670449719,
        "AUPRC": 0.9777027201855811
    }, {
        "model": "MLP",
        "run_type": "train",
        "holdout": 42,
        "Accuracy": 0.9967970773330664,
        "Balanced Accuracy": 0.9903044988683234,
        "AUROC": 0.999758125845986,
        "AUPRC": 0.9980171943710833
    }, {
        "model": "MLP",
        "run_type": "test",
        "holdout": 42,
        "Accuracy": 0.9819337403663297,
        "Balanced Accuracy": 0.9550461666988049,
        "AUROC": 0.9965379980226814,
        "AUPRC": 0.9731419376025342
    }, {
        "model": "FFNN_1",
        "run_type": "train",
        "holdout": 42,
        "Accuracy": 0.9954708671662892,
        "Balanced Accuracy": 0.989791124590335,
        "AUROC": 0.9996152800145099,
        "AUPRC": 0.9962630303539506
    }, {
        "model": "FFNN_1",
        "run_type": "test",
        "holdout": 42,
        "Accuracy": 0.980832749474527,
        "Balanced Accuracy": 0.9553680894463349,
        "AUROC": 0.9957105580713933,
        "AUPRC": 0.957803946280941
    }, {
        "model": "FFNN_2",
        "run_type": "train",
        "holdout": 42,
        "Accuracy": 0.9978855705831571,
        "Balanced Accuracy": 0.9934694193369767,
        "AUROC": 0.9998566083401016,
        "AUPRC": 0.9991663929236887
    }, {
        "model": "FFNN_2",
        "run_type": "test",
        "holdout": 42,
        "Accuracy": 0.9886898208387549,
        "Balanced Accuracy": 0.9715155964288803,
        "AUROC": 0.9985501809823799,
        "AUPRC": 0.9866848807696852
    }, {
        "model": "FFNN_3",
        "run_type": "train",
        "holdout": 42,
        "Accuracy": 0.9966219174997185,
        "Balanced Accuracy": 0.9880334672509165,
        "AUROC": 0.9997067081944598,
        "AUPRC": 0.9983057198745496
    }, {
        "model": "FFNN_3",
        "run_type": "test",
        "holdout": 42,
        "Accuracy": 0.9824341907716945,
        "Balanced Accuracy": 0.9523077724903393,
        "AUROC": 0.9964903248668904,
        "AUPRC": 0.9760535765465727
    }, {
        "model": "MLP",
        "run_type": "train",
        "holdout": 43,
        "Accuracy": 0.9964968033330414,
        "Balanced Accuracy": 0.9890960040338793,
        "AUROC": 0.9998021590761433,
        "AUPRC": 0.9982347461188251
    }, {
        "model": "MLP",
        "run_type": "test",
        "holdout": 43,
        "Accuracy": 0.9832349114202783,
        "Balanced Accuracy": 0.9529491127500099,
        "AUROC": 0.9966414372270169,
        "AUPRC": 0.9730213968823677
    }, {
        "model": "FFNN_1",
        "run_type": "train",
        "holdout": 43,
        "Accuracy": 0.9952456616662705,
        "Balanced Accuracy": 0.9879639950384427,
        "AUROC": 0.9995837056443587,
        "AUPRC": 0.9955823466987851
    }, {
        "model": "FFNN_1",
        "run_type": "test",
        "holdout": 43,
        "Accuracy": 0.982684415974377,
        "Balanced Accuracy": 0.9558480507930089,
        "AUROC": 0.9957264245621923,
        "AUPRC": 0.9592873033654524
    }, {
        "model": "FFNN_2",
        "run_type": "train",
        "holdout": 43,
        "Accuracy": 0.9979981733331665,
        "Balanced Accuracy": 0.9941468922088053,
        "AUROC": 0.9998455697087613,
        "AUPRC": 0.9991659955436586
    }, {
        "model": "FFNN_2",
        "run_type": "test",
        "holdout": 43,
        "Accuracy": 0.9886898208387549,
        "Balanced Accuracy": 0.9694385106798062,
        "AUROC": 0.9978429923297797,
        "AUPRC": 0.9845094238808294
    }, {
        "model": "FFNN_3",
        "run_type": "train",
        "holdout": 43,
        "Accuracy": 0.9961589950830132,
        "Balanced Accuracy": 0.9873941140841589,
        "AUROC": 0.9996126360861188,
        "AUPRC": 0.9970379564692253
    }, {
        "model": "FFNN_3",
        "run_type": "test",
        "holdout": 43,
        "Accuracy": 0.9820838754879392,
        "Balanced Accuracy": 0.9504103636970564,
        "AUROC": 0.995898868264825,
        "AUPRC": 0.9715719333736407
    }, {
        "model": "MLP",
        "run_type": "train",
        "holdout": 44,
        "Accuracy": 0.9963341549163611,
        "Balanced Accuracy": 0.9871625715179175,
        "AUROC": 0.9996643431572162,
        "AUPRC": 0.9977104321869826
    }, {
        "model": "MLP",
        "run_type": "test",
        "holdout": 44,
        "Accuracy": 0.9817335602041838,
        "Balanced Accuracy": 0.9473799990406422,
        "AUROC": 0.9966333566148297,
        "AUPRC": 0.9764673563657658
    }, {
        "model": "FFNN_1",
        "run_type": "train",
        "holdout": 44,
        "Accuracy": 0.9956335155829694,
        "Balanced Accuracy": 0.9902607873007667,
        "AUROC": 0.9997095233179821,
        "AUPRC": 0.9970700897755141
    }, {
        "model": "FFNN_1",
        "run_type": "test",
        "holdout": 44,
        "Accuracy": 0.9835351816634972,
        "Balanced Accuracy": 0.9604830187162943,
        "AUROC": 0.9966272654542752,
        "AUPRC": 0.9672951751251218
    }, {
        "model": "FFNN_2",
        "run_type": "train",
        "holdout": 44,
        "Accuracy": 0.99776045641648,
        "Balanced Accuracy": 0.9941542090733512,
        "AUROC": 0.9998262814681024,
        "AUPRC": 0.9989544012374174
    }, {
        "model": "FFNN_2",
        "run_type": "test",
        "holdout": 44,
        "Accuracy": 0.9888900010009009,
        "Balanced Accuracy": 0.9699292912048039,
        "AUROC": 0.9983776021935251,
        "AUPRC": 0.9859737608793208
    }, {
        "model": "FFNN_3",
        "run_type": "train",
        "holdout": 44,
        "Accuracy": 0.9964968033330414,
        "Balanced Accuracy": 0.9877266709899962,
        "AUROC": 0.9996698866551582,
        "AUPRC": 0.9979833727205039
    }, {
        "model": "FFNN_3",
        "run_type": "test",
        "holdout": 44,
        "Accuracy": 0.9841357221499349,
        "Balanced Accuracy": 0.9568570589071962,
        "AUROC": 0.9970349433916276,
        "AUPRC": 0.9783340348062302
    }, {
        "model": "MLP",
        "run_type": "train",
        "holdout": 45,
        "Accuracy": 0.9962715978330227,
        "Balanced Accuracy": 0.9893464832382233,
        "AUROC": 0.9997288407309052,
        "AUPRC": 0.9977757986014524
    }, {
        "model": "MLP",
        "run_type": "test",
        "holdout": 45,
        "Accuracy": 0.9830847762986687,
        "Balanced Accuracy": 0.9551301780483072,
        "AUROC": 0.9959918567078059,
        "AUPRC": 0.9717884206830129
    }, {
        "model": "FFNN_1",
        "run_type": "train",
        "holdout": 45,
        "Accuracy": 0.9954458443329538,
        "Balanced Accuracy": 0.9884548690559151,
        "AUROC": 0.9996414621218797,
        "AUPRC": 0.9962589672079617
    }, {
        "model": "FFNN_1",
        "run_type": "test",
        "holdout": 45,
        "Accuracy": 0.985386848163347,
        "Balanced Accuracy": 0.9626624138576654,
        "AUROC": 0.9966539634039636,
        "AUPRC": 0.9602555380262536
    }, {
        "model": "FFNN_2",
        "run_type": "train",
        "holdout": 45,
        "Accuracy": 0.9977729678331477,
        "Balanced Accuracy": 0.9930752567500897,
        "AUROC": 0.9998713134644724,
        "AUPRC": 0.9989597728099571
    }, {
        "model": "FFNN_2",
        "run_type": "test",
        "holdout": 45,
        "Accuracy": 0.989740766690021,
        "Balanced Accuracy": 0.9734313032649579,
        "AUROC": 0.9985043499114338,
        "AUPRC": 0.9883475105106485
    }, {
        "model": "FFNN_3",
        "run_type": "train",
        "holdout": 45,
        "Accuracy": 0.9964968033330414,
        "Balanced Accuracy": 0.987868326132467,
        "AUROC": 0.9997472131159975,
        "AUPRC": 0.9983483917166363
    }, {
        "model": "FFNN_3",
        "run_type": "test",
        "holdout": 45,
        "Accuracy": 0.9835852267040336,
        "Balanced Accuracy": 0.9535247397029729,
        "AUROC": 0.9971257950161878,
        "AUPRC": 0.9778149817551215
    }, {
        "model": "MLP",
        "run_type": "train",
        "holdout": 46,
        "Accuracy": 0.9964342462497029,
        "Balanced Accuracy": 0.9897689275678314,
        "AUROC": 0.9997603268165719,
        "AUPRC": 0.9976882998338241
    }, {
        "model": "MLP",
        "run_type": "test",
        "holdout": 46,
        "Accuracy": 0.9820338304474027,
        "Balanced Accuracy": 0.952647993280664,
        "AUROC": 0.9968331736982605,
        "AUPRC": 0.9762310655256036
    }, {
        "model": "FFNN_1",
        "run_type": "train",
        "holdout": 46,
        "Accuracy": 0.9952331502496028,
        "Balanced Accuracy": 0.9900345333589988,
        "AUROC": 0.9995192441521548,
        "AUPRC": 0.9955653945220329
    }, {
        "model": "FFNN_1",
        "run_type": "test",
        "holdout": 46,
        "Accuracy": 0.982684415974377,
        "Balanced Accuracy": 0.9573586586105174,
        "AUROC": 0.9963445299916834,
        "AUPRC": 0.9657192584079064
    }, {
        "model": "FFNN_2",
        "run_type": "train",
        "holdout": 46,
        "Accuracy": 0.9975852965831321,
        "Balanced Accuracy": 0.9930164185957095,
        "AUROC": 0.9998542691851052,
        "AUPRC": 0.9990457282778994
    }, {
        "model": "FFNN_2",
        "run_type": "test",
        "holdout": 46,
        "Accuracy": 0.9880392353117806,
        "Balanced Accuracy": 0.9724697104146836,
        "AUROC": 0.9976042826949859,
        "AUPRC": 0.9841247201995443
    }, {
        "model": "FFNN_3",
        "run_type": "train",
        "holdout": 46,
        "Accuracy": 0.9960964379996747,
        "Balanced Accuracy": 0.9875948538098754,
        "AUROC": 0.9996292481553571,
        "AUPRC": 0.997507492958324
    }, {
        "model": "FFNN_3",
        "run_type": "test",
        "holdout": 46,
        "Accuracy": 0.9846361725552998,
        "Balanced Accuracy": 0.9595946180371986,
        "AUROC": 0.9962764956580709,
        "AUPRC": 0.9770311325920171
    }, {
        "model": "MLP",
        "run_type": "train",
        "holdout": 47,
        "Accuracy": 0.9965468489997122,
        "Balanced Accuracy": 0.9882271365409527,
        "AUROC": 0.9997978937839999,
        "AUPRC": 0.9983057200695101
    }, {
        "model": "MLP",
        "run_type": "test",
        "holdout": 47,
        "Accuracy": 0.9829846862175958,
        "Balanced Accuracy": 0.9512970942192258,
        "AUROC": 0.9969240621645179,
        "AUPRC": 0.9761613995897874
    }, {
        "model": "FFNN_1",
        "run_type": "train",
        "holdout": 47,
        "Accuracy": 0.9954958899996247,
        "Balanced Accuracy": 0.9892386448918129,
        "AUROC": 0.9996375407553807,
        "AUPRC": 0.9968809131936296
    }, {
        "model": "FFNN_1",
        "run_type": "test",
        "holdout": 47,
        "Accuracy": 0.9838354519067161,
        "Balanced Accuracy": 0.9610303635266022,
        "AUROC": 0.9970774341487211,
        "AUPRC": 0.9758447094141116
    }, {
        "model": "FFNN_2",
        "run_type": "train",
        "holdout": 47,
        "Accuracy": 0.9978105020831509,
        "Balanced Accuracy": 0.9928603761530126,
        "AUROC": 0.9998163375643709,
        "AUPRC": 0.9983250617778807
    }, {
        "model": "FFNN_2",
        "run_type": "test",
        "holdout": 47,
        "Accuracy": 0.9883395055549995,
        "Balanced Accuracy": 0.9698070136127859,
        "AUROC": 0.9979298404899435,
        "AUPRC": 0.9848255969540798
    }, {
        "model": "FFNN_3",
        "run_type": "train",
        "holdout": 47,
        "Accuracy": 0.9964467576663706,
        "Balanced Accuracy": 0.9883122281979815,
        "AUROC": 0.9997288699031696,
        "AUPRC": 0.9981025810999806
    }, {
        "model": "FFNN_3",
        "run_type": "test",
        "holdout": 47,
        "Accuracy": 0.9846862175958363,
        "Balanced Accuracy": 0.9583011183395339,
        "AUROC": 0.9971009637124759,
        "AUPRC": 0.978543241872259
    }, {
        "model": "MLP",
        "run_type": "train",
        "holdout": 48,
        "Accuracy": 0.9966594517497216,
        "Balanced Accuracy": 0.9890934829360754,
        "AUROC": 0.9997530498719669,
        "AUPRC": 0.997737408584011
    }, {
        "model": "MLP",
        "run_type": "test",
        "holdout": 48,
        "Accuracy": 0.983935541987789,
        "Balanced Accuracy": 0.954478018610313,
        "AUROC": 0.9970869270259562,
        "AUPRC": 0.9774971163402375
    }, {
        "model": "FFNN_1",
        "run_type": "train",
        "holdout": 48,
        "Accuracy": 0.9956460269996372,
        "Balanced Accuracy": 0.9884735592651519,
        "AUROC": 0.9995475719563458,
        "AUPRC": 0.9959245727190471
    }, {
        "model": "FFNN_1",
        "run_type": "test",
        "holdout": 48,
        "Accuracy": 0.9838354519067161,
        "Balanced Accuracy": 0.9559320621425111,
        "AUROC": 0.996482416182622,
        "AUPRC": 0.9709318580603166
    }, {
        "model": "FFNN_2",
        "run_type": "train",
        "holdout": 48,
        "Accuracy": 0.9977104107498092,
        "Balanced Accuracy": 0.9933704332374533,
        "AUROC": 0.9998496346335088,
        "AUPRC": 0.9988472408896673
    }, {
        "model": "FFNN_2",
        "run_type": "test",
        "holdout": 48,
        "Accuracy": 0.9884896406766089,
        "Balanced Accuracy": 0.9712136418810712,
        "AUROC": 0.9980026396830219,
        "AUPRC": 0.9847995698471216
    }, {
        "model": "FFNN_3",
        "run_type": "train",
        "holdout": 48,
        "Accuracy": 0.9966469403330539,
        "Balanced Accuracy": 0.9882364816455712,
        "AUROC": 0.9996937940935898,
        "AUPRC": 0.9982223697950035
    }, {
        "model": "FFNN_3",
        "run_type": "test",
        "holdout": 48,
        "Accuracy": 0.9830847762986687,
        "Balanced Accuracy": 0.9572072637973812,
        "AUROC": 0.9959823638305707,
        "AUPRC": 0.9677299093971894
    }, {
        "model": "MLP",
        "run_type": "train",
        "holdout": 49,
        "Accuracy": 0.9959713238329976,
        "Balanced Accuracy": 0.9902628155408391,
        "AUROC": 0.9996870054005692,
        "AUPRC": 0.9974799837105183
    }, {
        "model": "MLP",
        "run_type": "test",
        "holdout": 49,
        "Accuracy": 0.9808827945150635,
        "Balanced Accuracy": 0.9433115090489225,
        "AUROC": 0.9962154366857385,
        "AUPRC": 0.9716188354947883
    }, {
        "model": "FFNN_1",
        "run_type": "train",
        "holdout": 49,
        "Accuracy": 0.9957711411663143,
        "Balanced Accuracy": 0.9910940561864262,
        "AUROC": 0.999552488250602,
        "AUPRC": 0.9954148701901798
    }, {
        "model": "FFNN_1",
        "run_type": "test",
        "holdout": 49,
        "Accuracy": 0.9841357221499349,
        "Balanced Accuracy": 0.9617665343140986,
        "AUROC": 0.997108540821472,
        "AUPRC": 0.9685405088343269
    }, {
        "model": "FFNN_2",
        "run_type": "train",
        "holdout": 49,
        "Accuracy": 0.9978230134998186,
        "Balanced Accuracy": 0.9929146649695164,
        "AUROC": 0.9998647619880235,
        "AUPRC": 0.9990375468050281
    }, {
        "model": "FFNN_2",
        "run_type": "test",
        "holdout": 49,
        "Accuracy": 0.9893404063657292,
        "Balanced Accuracy": 0.9711279603746428,
        "AUROC": 0.9983425166175088,
        "AUPRC": 0.9865504044395351
    }, {
        "model": "FFNN_3",
        "run_type": "train",
        "holdout": 49,
        "Accuracy": 0.9966969859997248,
        "Balanced Accuracy": 0.988595292054057,
        "AUROC": 0.9997966117397452,
        "AUPRC": 0.9984130532266955
    }, {
        "model": "FFNN_3",
        "run_type": "test",
        "holdout": 49,
        "Accuracy": 0.983735361825643,
        "Balanced Accuracy": 0.9541760640625039,
        "AUROC": 0.9970907094401715,
        "AUPRC": 0.977271282703713
    }
]
